[
  {
    "zan": "38", 
    "publish_time": "@8 MONTHS AGO", 
    "auther": "光消失的地方", 
    "floor": "12074", 
    "url": "http://jandan.net/duan/page-483#comment-2856645", 
    "against": "10", 
    "content": "女首富身家蒸发百亿，赵薇身家缩水40亿，股市崩盘，金融危机要来了。朋友圈里疯狂在刷各种新闻。然而对于我这种买东西为了包邮10块钱而跟老板讨价还价半小时，钱因为买包已经花光进不去股市，可能只见过40亿精子的穷鬼来说，这一切跟我有什么关系啊！"
  }, 
  {
    "zan": "24", 
    "publish_time": "@8 MONTHS AGO", 
    "auther": "brian", 
    "floor": "12073", 
    "url": "http://jandan.net/duan/page-483#comment-2856629", 
    "against": "23", 
    "content": "前几天学校放假回家，看见桌子上放了一袋东西，名字是油切果。回来这几天天天出来吃饭，吃的油水比较大，就会拿出来一个油切果吃，还想这东西吃了应该会好点。后来就一直拉肚子，我想应该是夏天到了，饭店的菜不新鲜。后来我跟我爸说，桌上的油切果我每次出来吃饭回来之后都会吃一个，切切肚子里的油。我爸冷笑一下说，那东西是你妈买的，为了减肥，吃了会拉肚子。"
  }, 
  {
    "zan": "69", 
    "publish_time": "@8 MONTHS AGO", 
    "auther": "格雷潘", 
    "floor": "12072", 
    "url": "http://jandan.net/duan/page-483#comment-2856609", 
    "against": "39", 
    "content": "刚才叫了个优步专车，司机给我聊了他的人生观，他说：“我有房子，有车，有自己的生意，自己当老板，多么自由。除了天王老子谁也命令不了我。”我说：“前面那条路左拐。”“好的。”"
  }, 
  {
    "zan": "39", 
    "publish_time": "@8 MONTHS AGO", 
    "auther": "maylog", 
    "floor": "12071", 
    "url": "http://jandan.net/duan/page-483#comment-2856517", 
    "against": "19", 
    "content": "证监会主席尚福林，在位时股票十年上涨为零，故名为上浮零；\n继任主席郭树清在位时股票从3000点跌到2000点，故名哥输清；\n现任主席肖钢上任之后真的是削光所有股民，故名削光。\n上联：十年一梦上浮零；\n下联：一朝醒来哥输清。\n横批：削光！"
  }, 
  {
    "zan": "16", 
    "publish_time": "@8 MONTHS AGO", 
    "auther": "光消失的地方", 
    "floor": "12070", 
    "url": "http://jandan.net/duan/page-483#comment-2856507", 
    "against": "45", 
    "content": "陈凯歌：如今拍不出《霸王别姬》 与时局有关\n“其实对于《霸王别姬》，我还是想说，时代力量是大于个人力量的。不是我现在就拍不出来了，是现在这个环境决定电影不能再这么拍了。你说我硬扛，那是扛不过去的！……所谓‘时者，势也’，所有的事儿都别脱离的实际。”"
  }, 
  {
    "zan": "22", 
    "publish_time": "@8 MONTHS AGO", 
    "auther": "光消失的地方", 
    "floor": "12069", 
    "url": "http://jandan.net/duan/page-483#comment-2856505", 
    "against": "120", 
    "content": "郭敬明：我算是“中国梦”的代表\n“中国梦核心就是要成功，要白手起家，一路飞黄腾达，最后站在财富和地位的最高点。我不是富二代、官二代，我是从四川一个小镇来的，什么关系也没有，长得也不是说惊人的帅，个子也小小的，我有什么呢？只有凭我的脑子，这是我唯一拥有。所以我一路走到今天，会激励很多人”郭敬明赞同自己算是”中国梦”的代表，他信心满满地表示：“我的成功模式基本不可能被复制。”"
  }, 
  {
    "zan": "25", 
    "publish_time": "@8 MONTHS AGO", 
    "auther": "光消失的地方", 
    "floor": "12068", 
    "url": "http://jandan.net/duan/page-483#comment-2856501", 
    "against": "23", 
    "content": "谷大白话：CNN报道《汽车人总动员》事件。导演表示听说过《赛车总动员》但没看过，坚称自己电影是原创，否认抄袭皮克斯。“街上的车还不是长得都很像。难道有人跟你长得像就犯法吗？”迪士尼已向导演发出律师函，但拒绝说明为何发函。【每日一词】knock-off: 山寨，抄袭。deny: 否认。shamelessly: 无耻地。\n导演还说这部电影的目的是教孩子们思考和创新。”Our goal is to teach children about thinking and innovation. ”"
  }, 
  {
    "zan": "227", 
    "publish_time": "@8 MONTHS AGO", 
    "auther": "光消失的地方", 
    "floor": "12067", 
    "url": "http://jandan.net/duan/page-483#comment-2856500", 
    "against": "7", 
    "content": "就如当年阉割Wi-Fi的iPhone一样，我们总是看到一些特色国行产品，例如刚刚被广电总局阉割了互联网功能的智能电视。他们不管科技发展潮流如何，不管用户是否方便，只管守着自己的私心利益。因为监管划分的问题，广电总局不惜毁了中国智能电视也要顽抗到底。"
  }, 
  {
    "zan": "12", 
    "publish_time": "@8 MONTHS AGO", 
    "auther": "光消失的地方", 
    "floor": "12066", 
    "url": "http://jandan.net/duan/page-483#comment-2856499", 
    "against": "22", 
    "content": "网络安全法草案征求意见，以后上网要注意了…草案规定：用户办理网络接入、固话移动电话入网等，应提供真实身份信息，不提供真实信息的不会被提供服务。处置重大突发社会安全事件时，国务院或者省、自治区、直辖市政府经国务院批准，可在部分地区临时限网。"
  }, 
  {
    "zan": "40", 
    "publish_time": "@8 MONTHS AGO", 
    "auther": "离离", 
    "floor": "12065", 
    "url": "http://jandan.net/duan/page-483#comment-2856459", 
    "against": "9", 
    "content": "白云山风油精相比漳州水仙牌味道更旖旎一些，水仙牌辛辣，但之后有毛茸茸的感觉；白云山清淡，但之后是爽朗开阔。"
  }, 
  {
    "zan": "51", 
    "publish_time": "@8 MONTHS AGO", 
    "auther": "moon", 
    "floor": "12064", 
    "url": "http://jandan.net/duan/page-483#comment-2856345", 
    "against": "16", 
    "content": "记得刚结婚那会，每天早上刷牙的时候，老婆都会帮我挤好牙膏，感觉超幸福。 后来好长一段时间没有，于是问她为什么。 结果她说：结婚后前几天，牙膏老是爱挤多了，然后掉地上了，觉得可惜，就用我的牙刷刮起来了。。。"
  }, 
  {
    "zan": "75", 
    "publish_time": "@8 MONTHS AGO", 
    "auther": "moon", 
    "floor": "12063", 
    "url": "http://jandan.net/duan/page-483#comment-2856344", 
    "against": "9", 
    "content": "话说张无忌重振明教之后无心教主之位，决意隐退江湖，和自己心爱的女人相守余生！赵敏、小昭、珠儿、芷若纷纷表态愿与无忌相知相守，浪迹天涯！张无忌在感动之余却不知道该如何选择，遂到少林求助于圆音大师，大师听后半睁开右眼看着无忌微微一笑，左手抬起拍了一下自己的胸膛，无忌恍然大悟，大师你是不是说让我跟从自己的本心！大师突然睁大眼睛咆哮到:“傻叉，我让你选胸大的”。"
  }, 
  {
    "zan": "111", 
    "publish_time": "@8 MONTHS AGO", 
    "auther": "屁屁兔", 
    "floor": "12062", 
    "url": "http://jandan.net/duan/page-483#comment-2856252", 
    "against": "9", 
    "content": "原先以为《汽车人总动员》导演卓建荣只是单纯地抄袭皮克斯动画，现在发现这逼是拿去年自己拍的动画片《K时代》直接剪成电影骗观众钱，底线再次刷新，这已经是涉嫌诈骗，应该受到法律的严惩。[怒]可自行百度K时代"
  }, 
  {
    "zan": "195", 
    "publish_time": "@8 MONTHS AGO", 
    "auther": "光消失的地方", 
    "floor": "12061", 
    "url": "http://jandan.net/duan/page-483#comment-2856213", 
    "against": "19", 
    "content": "道士下山如果把王宝强这个 NC 去掉，讲郭富城、张震和郭富城师兄元华之间的三角恋，让郭富城和张震在滚草地的时候热吻一下，能感动国内一帮文艺 LGBT，豆瓣评分上 9.0 绝对没问题。"
  }, 
  {
    "zan": "186", 
    "publish_time": "@8 MONTHS AGO", 
    "auther": "光消失的地方", 
    "floor": "12060", 
    "url": "http://jandan.net/duan/page-483#comment-2856210", 
    "against": "8", 
    "content": "北美留学生求婚三大圣地：1.帝国大厦顶，2.芝加哥sky deck，3.佛罗里达key west长桥落日，高峰期为东部时间晚上八点半左右。你好好看个风景旁边儿扑通一下就跪下来了，遇到法定节假日成片成片的跪，还以为是过来上访的。"
  }, 
  {
    "zan": "248", 
    "publish_time": "@8 MONTHS AGO", 
    "auther": "iloveinet", 
    "floor": "12059", 
    "url": "http://jandan.net/duan/page-483#comment-2856209", 
    "against": "9", 
    "content": "近日，认识了一位老中医。当他听到我的职业之后，他建议我：“做你们这一行，夏天多坐公交或者步行，少喝饮料，不能喝啤酒，更不能喝红酒，多喝点白开水，在家尽量不要用空调，多运动，不要在外面吃饭，特别是海鲜。”几番追究原由，老中医无奈直言：“因为你们挣得不多啊……”"
  }, 
  {
    "zan": "45", 
    "publish_time": "@8 MONTHS AGO", 
    "auther": "刘北习", 
    "floor": "12058", 
    "url": "http://jandan.net/duan/page-483#comment-2856186", 
    "against": "13", 
    "content": "“为什么我来姨妈就会长痘痘？”“废话，你亲戚来你家不带点水果什么的啊？”"
  }, 
  {
    "zan": "61", 
    "publish_time": "@8 MONTHS AGO", 
    "auther": "Sloven", 
    "floor": "12057", 
    "url": "http://jandan.net/duan/page-483#comment-2856134", 
    "against": "15", 
    "content": "不不不，我从不歧视女性，我只是歧视女权逗士而已。"
  }, 
  {
    "zan": "97", 
    "publish_time": "@8 MONTHS AGO", 
    "auther": "", 
    "floor": "12056", 
    "url": "http://jandan.net/duan/page-483#comment-2856119", 
    "against": "12", 
    "content": "根据我看电影多年的经验，一旦编剧里有陈凯歌，这部电影基本上就是烂片。《霸王别姬》的成功是因为李碧华让陈凯歌别管他们的事。老实说，我看《道士下山》的时候心理怕极了，觉得陈凯歌会从荧幕后面走出来，打我一记耳光，问我：“深刻不深刻？”我答：“不深刻。”他又打了我一耳光，一会儿我就被打死了。"
  }, 
  {
    "zan": "43", 
    "publish_time": "@8 MONTHS AGO", 
    "auther": "屁屁兔", 
    "floor": "12055", 
    "url": "http://jandan.net/duan/page-483#comment-2856117", 
    "against": "5", 
    "content": "今年暑假我只看《汽车人总动员》，因为有种被我一个人包场的感觉。"
  }, 
  {
    "zan": "46", 
    "publish_time": "@8 MONTHS AGO", 
    "auther": "", 
    "floor": "12054", 
    "url": "http://jandan.net/duan/page-483#comment-2856115", 
    "against": "10", 
    "content": "“拿不出来证据，看我弄死你！”“那我要是拿出来了呢？”“看我弄不死你！” @话提"
  }, 
  {
    "zan": "215", 
    "publish_time": "@8 MONTHS AGO", 
    "auther": "", 
    "floor": "12053", 
    "url": "http://jandan.net/duan/page-483#comment-2856112", 
    "against": "12", 
    "content": "家长批学生午餐差请局长试吃 菊长拿着牙签说：九菜一汤很照顾学生的发育，不错不错，但是我要批评你们学校，谁让你们给学生供应茅台的？@网易网友"
  }, 
  {
    "zan": "67", 
    "publish_time": "@8 MONTHS AGO", 
    "auther": "段子大百科", 
    "floor": "12052", 
    "url": "http://jandan.net/duan/page-483#comment-2855979", 
    "against": "12", 
    "content": "这一段时间陆续有几个搞网络的加我，说认识我，我咋一点印象都没。有个还能说出我的名字，做了什么事，弄得我一头雾水。推测两个原因。1.我虽不在网络江湖，但江湖依然有哥的传说。2.个人资料泄露了。"
  }, 
  {
    "zan": "150", 
    "publish_time": "@8 MONTHS AGO", 
    "auther": "段子大百科", 
    "floor": "12051", 
    "url": "http://jandan.net/duan/page-483#comment-2855978", 
    "against": "8", 
    "content": "记者去采访一山区百岁老农：“老人家，你是吃什么东西才能保持长寿的啊？”“我们这只能种玉米，平时也是以玉米为主食。”“那你现在最大的愿望是什么呢？”“我最想死。”“啊！为什么？”“吃了一百年的玉米，你不想死啊？”"
  }, 
  {
    "zan": "72", 
    "publish_time": "@8 MONTHS AGO", 
    "auther": "段子大百科", 
    "floor": "12050", 
    "url": "http://jandan.net/duan/page-483#comment-2855977", 
    "against": "56", 
    "content": "同学和女朋友分手了！女的在个性签名上写到：“曾经牵过的那条狗，现在在舔谁的手。”那哥们儿气不过了，回到：“曾经用过的那个洞，谁知现在谁再用。”"
  }
]