[
  {
    "zan": "79", 
    "publish_time": "@5 MONTHS AGO", 
    "auther": "maylog", 
    "floor": "16749", 
    "url": "http://jandan.net/duan/page-670#comment-2953797", 
    "against": "15", 
    "content": "緊張有時候是個好東西。去喝喜酒時，新郎新娘上台致詞，新娘非常落落大方、輕鬆自然而愉快，害我第一個想法是：新娘真是駕輕就熟，經驗豐富……(`L_` )"
  }, 
  {
    "zan": "15", 
    "publish_time": "@5 MONTHS AGO", 
    "auther": "杜早", 
    "floor": "16748", 
    "url": "http://jandan.net/duan/page-670#comment-2953741", 
    "against": "16", 
    "content": "【韩议员称游戏业受中国冲击 年损失55亿元】　近日，韩国全兵贤议员在“振兴危机的游戏产业座谈会”上发表声明称，每年韩国游戏业损失金额为55亿以上人民币，造成这一现象的重要原因，是韩国游戏产业受到中国资本影响逐渐扩大所导致的。"
  }, 
  {
    "zan": "54", 
    "publish_time": "@5 MONTHS AGO", 
    "auther": "光消失的地方", 
    "floor": "16747", 
    "url": "http://jandan.net/duan/page-670#comment-2953694", 
    "against": "58", 
    "content": "黄牛无处不在，无所不能，说什么票他都能搞的到……直到有一天，他遇到了单身狗，单身狗：我就要个女票，黄牛卒。[doge]"
  }, 
  {
    "zan": "86", 
    "publish_time": "@5 MONTHS AGO", 
    "auther": "maylog", 
    "floor": "16746", 
    "url": "http://jandan.net/duan/page-670#comment-2953686", 
    "against": "82", 
    "content": "腐女是不能去西藏看天葬的。\n为什么？\n秃鹫是食腐动物。"
  }, 
  {
    "zan": "59", 
    "publish_time": "@5 MONTHS AGO", 
    "auther": "光消失的地方", 
    "floor": "16745", 
    "url": "http://jandan.net/duan/page-670#comment-2953682", 
    "against": "21", 
    "content": "最近随份子的时候可以想想，人家TFboys还没成年就开始随"
  }, 
  {
    "zan": "121", 
    "publish_time": "@5 MONTHS AGO", 
    "auther": "缓缓飘落叶", 
    "floor": "16744", 
    "url": "http://jandan.net/duan/page-670#comment-2953680", 
    "against": "20", 
    "content": "记得拿到驾照那会，我爸带着我在每个豪车4S店都看了下，我感动哭了，然后我爸告诉我：看好了没？以后这些车别撞。"
  }, 
  {
    "zan": "221", 
    "publish_time": "@5 MONTHS AGO", 
    "auther": "光消失的地方", 
    "floor": "16743", 
    "url": "http://jandan.net/duan/page-670#comment-2953673", 
    "against": "5", 
    "content": "噩梦有多强大？这么说吧，作者是你，编剧是你，导演是你，演员是你，观众也是你，可最终被吓成狗的，还是你。"
  }, 
  {
    "zan": "126", 
    "publish_time": "@5 MONTHS AGO", 
    "auther": "光消失的地方", 
    "floor": "16742", 
    "url": "http://jandan.net/duan/page-670#comment-2953652", 
    "against": "12", 
    "content": "发现自己有一种很厉害的超能力：心想事砸。"
  }, 
  {
    "zan": "83", 
    "publish_time": "@5 MONTHS AGO", 
    "auther": "刘北习", 
    "floor": "16741", 
    "url": "http://jandan.net/duan/page-670#comment-2953651", 
    "against": "11", 
    "content": "“我没想到你是这样的人！”……“好笑！我凭什么非要成为你想象中的人？”"
  }, 
  {
    "zan": "379", 
    "publish_time": "@5 MONTHS AGO", 
    "auther": "光消失的地方", 
    "floor": "16740", 
    "url": "http://jandan.net/duan/page-670#comment-2953649", 
    "against": "17", 
    "content": "“你喜欢动漫你是汉奸？”“我喜欢你妈我是你爸？”"
  }, 
  {
    "zan": "241", 
    "publish_time": "@5 MONTHS AGO", 
    "auther": "光消失的地方", 
    "floor": "16739", 
    "url": "http://jandan.net/duan/page-670#comment-2953643", 
    "against": "11", 
    "content": "【人民日报刊文：“青岛大虾”影响难挽回，要归咎于公权力麻痹】在一段时间内，“天价大虾”会像狗皮膏药一样糊上青岛，这个恶果本来有机会避免。如果派出所能给消费者撑腰，如果物价局能够迅速处理……正是职能部门的不作为，导致了事态激化，有欺诈不可怕，怕的就是公权力麻痹。"
  }, 
  {
    "zan": "45", 
    "publish_time": "@5 MONTHS AGO", 
    "auther": "MK", 
    "floor": "16738", 
    "url": "http://jandan.net/duan/page-670#comment-2953627", 
    "against": "36", 
    "content": "青島三十八元一隻蝦好意說自己宰客。too young too simple\n我大香港藥房一支藥油萬多元。jc大叔也無可奈何。。。"
  }, 
  {
    "zan": "14", 
    "publish_time": "@5 MONTHS AGO", 
    "auther": "妙赢天", 
    "floor": "16737", 
    "url": "http://jandan.net/duan/page-670#comment-2953589", 
    "against": "27", 
    "content": "我自问不仇富，可现在我在想自己是不是得了富人病。生活那么美好，有事没事儿呻吟个毛。\n对，这话在理。＃富人的文艺就像聪明人的叹息，卖弄风姿\n＃听说某干爹画画不错，买一副镇家"
  }, 
  {
    "zan": "56", 
    "publish_time": "@5 MONTHS AGO", 
    "auther": "lsk", 
    "floor": "16736", 
    "url": "http://jandan.net/duan/page-670#comment-2953572", 
    "against": "18", 
    "content": "为了早起，我的闹钟是这样设定的：\n7：00\n7：10\n7：20\n7：30\n7：35\n……\n7：40"
  }, 
  {
    "zan": "188", 
    "publish_time": "@5 MONTHS AGO", 
    "auther": "CRKeys", 
    "floor": "16735", 
    "url": "http://jandan.net/duan/page-670#comment-2953568", 
    "against": "19", 
    "content": "今天在路上捡到了一个U型锁， 打开的那种， 我本来想丢掉， 正好看见停在路边的电动车没上锁， 这时一股雷锋精神涌上心头， 于是用锁把电动车锁上了！"
  }, 
  {
    "zan": "293", 
    "publish_time": "@5 MONTHS AGO", 
    "auther": "CRKeys", 
    "floor": "16734", 
    "url": "http://jandan.net/duan/page-670#comment-2953564", 
    "against": "15", 
    "content": "电梯坏了。老实巴交的肯德基小哥也不知道打个电话。像圣斗士一样背着四四方方的大箱子一层层地爬楼。我看着有些不忍，就上前与他攀谈，希望借此减轻爬楼的枯燥与疲累。终于，小哥到达了13楼。他感激地对我说，谢谢你，大哥。我说，不必客气。把我订的肯德基给我吧"
  }, 
  {
    "zan": "96", 
    "publish_time": "@5 MONTHS AGO", 
    "auther": "光消失的地方", 
    "floor": "16733", 
    "url": "http://jandan.net/duan/page-670#comment-2953536", 
    "against": "5", 
    "content": "深深感觉到贝爷是喜欢蹭别人零食吃的馋逼的天敌：“你在吃啥呢？分我一点？” “蟑螂，吃吗？” “…不了…” ；“你在喝啥捏？我尝尝呢？” “我自己的尿，来点吗？” “……”"
  }, 
  {
    "zan": "112", 
    "publish_time": "@5 MONTHS AGO", 
    "auther": "光消失的地方", 
    "floor": "16732", 
    "url": "http://jandan.net/duan/page-670#comment-2953532", 
    "against": "10", 
    "content": "【旧闻重温：游客在青岛吃顿烧烤 花1万8还被打】2008年10月，日照游客韩先生等13人在青岛吃烧烤，结账时一算，总计18000多元。摊主称，15元、20元不是一串的价格，而是每块肉的价格。双方发生冲突。韩先生向中山路派出所报案。【亮点】经过派出所调解，韩先生及朋友支付了18000多元的餐费。说好的在青岛吃饭打110可以打八折呢？"
  }, 
  {
    "zan": "143", 
    "publish_time": "@5 MONTHS AGO", 
    "auther": "光消失的地方", 
    "floor": "16731", 
    "url": "http://jandan.net/duan/page-670#comment-2953530", 
    "against": "15", 
    "content": "【哈佛辩论队完败于囚徒队】一方是获得多个次冠军的哈佛本科高材生；一方是纽约监狱的服刑人员，准备过程甚至不能上网，结果哈佛完败！辩题是：美国大学是否有权拒绝父母为非法移民的学生。囚徒队的观点是“有权拒绝”，与他们的实际想法并不同。囚徒队的手下败将还包括西点军校囚徒队：我是对的！哈佛队：你是错的！囚徒队：我快出狱了。哈佛队：你是对的！"
  }, 
  {
    "zan": "91", 
    "publish_time": "@5 MONTHS AGO", 
    "auther": "CRKeys", 
    "floor": "16730", 
    "url": "http://jandan.net/duan/page-670#comment-2953518", 
    "against": "6", 
    "content": "自己一个人看恐怖片实在是不敢点击。于是便把电影声音关掉，打开酷狗开了一首最炫民族风，声音调最大……，感觉贞子一直在里面动次打次动次打次。"
  }, 
  {
    "zan": "63", 
    "publish_time": "@5 MONTHS AGO", 
    "auther": "glare", 
    "floor": "16729", 
    "url": "http://jandan.net/duan/page-670#comment-2953489", 
    "against": "27", 
    "content": "你们这些人太乃义无。撕X抓不到重点。要是没有中医，现在能有这么多好吃的吗。"
  }, 
  {
    "zan": "132", 
    "publish_time": "@5 MONTHS AGO", 
    "auther": "光消失的地方", 
    "floor": "16728", 
    "url": "http://jandan.net/duan/page-670#comment-2953485", 
    "against": "5", 
    "content": "上飞机前，女神说：「我要上飞机了，晚点再联系你。」第三天，他忍不住问女神为什么一直没有联系他，女神说：「因为没有晚点啊。。」"
  }, 
  {
    "zan": "213", 
    "publish_time": "@5 MONTHS AGO", 
    "auther": "光消失的地方", 
    "floor": "16727", 
    "url": "http://jandan.net/duan/page-670#comment-2953484", 
    "against": "16", 
    "content": "今天在操场逛看到一对情侣，女的一直骂那个男的，但是那个男的特别有耐心的一直保持微笑，后来女的也笑了说，死样，吵个架也不严肃。下午和女友闹别扭了，没错，我学了，一直保持微笑，女友反手就一巴掌，你笑你妈了比你笑。"
  }, 
  {
    "zan": "142", 
    "publish_time": "@5 MONTHS AGO", 
    "auther": "屁屁兔", 
    "floor": "16726", 
    "url": "http://jandan.net/duan/page-670#comment-2953483", 
    "against": "3", 
    "content": "想到明天还要上一天班，我就觉得国家这安排太小家子气，既然已经放七天了，就不要在乎两天的双休日，硬是要抠出一天上班日来，斤斤计较的，实在太抠门儿。"
  }, 
  {
    "zan": "54", 
    "publish_time": "@5 MONTHS AGO", 
    "auther": "Yu", 
    "floor": "16725", 
    "url": "http://jandan.net/duan/page-670#comment-2953420", 
    "against": "7", 
    "content": "讲真：\n下个旅游季，青岛的餐饮等服务一定会规范很多吧。\n并且，人也一定会少了很多吧，可以去看看海，而不是看人海了吧。\n那么，去还是不去呢？\n觉得得还是不去了，因为没钱，哪都去不了。"
  }
]