[
  {
    "zan": "91", 
    "publish_time": "@10 MONTHS AGO", 
    "auther": "光消失的地方", 
    "floor": "9099", 
    "url": "http://jandan.net/duan/page-364#comment-2782005", 
    "against": "8", 
    "content": "我和一女的玩的很好，经常一起吃饭唱歌，有一天我哥们喊我去唱歌，于是我把她喊上一路，结束后我送她回家，在路上她缓缓的说，我喜欢你……！没等她说完我上去就是一个吻，啪！一个巴掌就落在我的脸上，她：我喜欢你哥们，你特么这是干嘛！我：……！！"
  }, 
  {
    "zan": "133", 
    "publish_time": "@10 MONTHS AGO", 
    "auther": "光消失的地方", 
    "floor": "9098", 
    "url": "http://jandan.net/duan/page-364#comment-2781987", 
    "against": "3", 
    "content": "世界三大权威杀毒软件测试机构纷纷取消了我国杀毒巨头的资格，我有预感，咱自主的测试标准即将出台了。"
  }, 
  {
    "zan": "183", 
    "publish_time": "@10 MONTHS AGO", 
    "auther": "光消失的地方", 
    "floor": "9097", 
    "url": "http://jandan.net/duan/page-364#comment-2781984", 
    "against": "30", 
    "content": "为什么故意变道？大家应该理解！看得出挺漂亮皮肤不错，80多次开房身体绝对很强壮， 貌似此女大概每月24日左右来大姨妈，因为23-30之间从不开房 由此可以推断出安全期大概就是每月16-23日1-5日，排卵期大致在每月6-15日，事发实在5月3日此天刚好在安全期，激情心切赶去开房，于是乎出了此事。 这就是此女司机强行变道的初衷"
  }, 
  {
    "zan": "89", 
    "publish_time": "@10 MONTHS AGO", 
    "auther": "光消失的地方", 
    "floor": "9096", 
    "url": "http://jandan.net/duan/page-364#comment-2781977", 
    "against": "11", 
    "content": "我国首部新写实主义公路片！讲两个北漂青年决定驾车公路行，影片进行一小时，车还没出五环，一直在开但没出五环！太写实了，观众纷纷起立鼓掌！这时车在一个转弯处突然变道！“必须勇爆自由了！”青年呐喊。被堵在后面的司机全跳出来暴揍两青年，青年高呼“自由万岁！”影片落幕！开放式结局，引人思考"
  }, 
  {
    "zan": "55", 
    "publish_time": "@10 MONTHS AGO", 
    "auther": "刘北习", 
    "floor": "9095", 
    "url": "http://jandan.net/duan/page-364#comment-2781975", 
    "against": "10", 
    "content": "老婆做了错事拒不悔改，我一时没忍住动起手来，有时候真的是不打不行，这不，十几巴掌过后，她摸着我红肿的脸庞心疼地说：“别打了，我知道错了还不行吗！“"
  }, 
  {
    "zan": "25", 
    "publish_time": "@10 MONTHS AGO", 
    "auther": "乔治克鲁尼美", 
    "floor": "9094", 
    "url": "http://jandan.net/duan/page-364#comment-2781934", 
    "against": "46", 
    "content": "上班中，刚才电脑点击了确定后画面变了（很多英文 排版画面什么都变了），就感觉像是大菠萝马上要开始那画面，就站在另一个次元的门口，已知的世界没有任何了解   那感觉到底究竟要怎么形容！！"
  }, 
  {
    "zan": "68", 
    "publish_time": "@10 MONTHS AGO", 
    "auther": "maylog", 
    "floor": "9093", 
    "url": "http://jandan.net/duan/page-364#comment-2781891", 
    "against": "18", 
    "content": "煎蛋技巧：\n1平底锅油要多，炒锅油可以少一些，需要晃锅让油铺满整个锅\n2小火热油，大火煎，别相信所谓热锅冷油可以不粘锅\n3蛋没打下去的时候放少许盐，可以不粘锅\n4煎的时候需要晃锅让煎蛋底部呈现漂亮的金黄色\n5煎完后可以把多余油倒掉"
  }, 
  {
    "zan": "59", 
    "publish_time": "@10 MONTHS AGO", 
    "auther": "光消失的地方", 
    "floor": "9092", 
    "url": "http://jandan.net/duan/page-364#comment-2781843", 
    "against": "8", 
    "content": "我问理发店小哥：你们是不是每天都度日如年啊？ ——没有啊。。——那为什么你们店每天都在搞周年庆？"
  }, 
  {
    "zan": "86", 
    "publish_time": "@10 MONTHS AGO", 
    "auther": "不吃狼的鱼", 
    "floor": "9091", 
    "url": "http://jandan.net/duan/page-364#comment-2781838", 
    "against": "18", 
    "content": "树上发现一只鸟。在中国:鸟儿回来了，春天来了！\n在美国:动物保护组织把它从树上救了下来。"
  }, 
  {
    "zan": "294", 
    "publish_time": "@10 MONTHS AGO", 
    "auther": "离离", 
    "floor": "9090", 
    "url": "http://jandan.net/duan/page-364#comment-2781833", 
    "against": "11", 
    "content": "真搞不懂某些“登山者”。补给是夏尔巴人背着，路是夏尔巴人带。他们就靠一罐一罐吸着夏尔巴人背的氧气向珠峰冲击。回来以后除了留给珠峰一堆翔，他得到了什么？眼睛被全封闭风镜挡着视野很窄，脸上还糊着氧气面罩。他们基本就看到了自己的脚尖，登山拐杖和雪、石头。你说这和去丽江客栈打一炮的“情怀”有啥区别？只剩下回来向朋友吹牛——自己“征服”了珠峰。不！你们这些2货，你没有征服珠峰。是夏尔巴人征服和珠峰。他们不但征服了珠峰，现在等于在圈养珠峰。以此来赚“高端”文青的钱。"
  }, 
  {
    "zan": "56", 
    "publish_time": "@10 MONTHS AGO", 
    "auther": "不吃狼的鱼", 
    "floor": "9089", 
    "url": "http://jandan.net/duan/page-364#comment-2781824", 
    "against": "17", 
    "content": "假如有一天智能AI统治了世界，人们不得不屈服于机器人的冷酷统治，任何违法规定的行为都会被处以极刑，那时候人类只是机器人的宠物，再也无法像昔日那般高傲……\n如果真的有那么一天，那么，关我屁事？"
  }, 
  {
    "zan": "53", 
    "publish_time": "@10 MONTHS AGO", 
    "auther": "不吃狼的鱼", 
    "floor": "9088", 
    "url": "http://jandan.net/duan/page-364#comment-2781822", 
    "against": "6", 
    "content": "有个成语叫嘉言懿行。\n我总觉得它是”郭嘉说话，司马懿执行”嗯。"
  }, 
  {
    "zan": "113", 
    "publish_time": "@10 MONTHS AGO", 
    "auther": "呵呵", 
    "floor": "9087", 
    "url": "http://jandan.net/duan/page-364#comment-2781772", 
    "against": "144", 
    "content": "判断一个女人是否适合谈恋爱，就跟他去旅行吧，如果连b都舍不得给你操，那还谈个鸭毛？"
  }, 
  {
    "zan": "87", 
    "publish_time": "@10 MONTHS AGO", 
    "auther": "光消失的地方", 
    "floor": "9086", 
    "url": "http://jandan.net/duan/page-364#comment-2781744", 
    "against": "6", 
    "content": "喝醉了打电话给前任，电话拨通后，我对她说：“要不你打过来吧，我接听免费。”"
  }, 
  {
    "zan": "42", 
    "publish_time": "@10 MONTHS AGO", 
    "auther": "光消失的地方", 
    "floor": "9085", 
    "url": "http://jandan.net/duan/page-364#comment-2781743", 
    "against": "3", 
    "content": "从小就懂得助人为乐的道理，为了让身边的人更快乐，我总是要求他们捐助我。"
  }, 
  {
    "zan": "31", 
    "publish_time": "@10 MONTHS AGO", 
    "auther": "光消失的地方", 
    "floor": "9084", 
    "url": "http://jandan.net/duan/page-364#comment-2781742", 
    "against": "93", 
    "content": "判断一个男人是否适合谈恋爱，就跟他去旅行吧，如果连五星酒店舍不得给你住，那还谈个鸡毛？"
  }, 
  {
    "zan": "105", 
    "publish_time": "@10 MONTHS AGO", 
    "auther": "光消失的地方", 
    "floor": "9083", 
    "url": "http://jandan.net/duan/page-364#comment-2781741", 
    "against": "5", 
    "content": "小时候一直向往那种流浪天涯隐居山林的日子，没想到长大后真的成了通缉犯。"
  }, 
  {
    "zan": "77", 
    "publish_time": "@10 MONTHS AGO", 
    "auther": "光消失的地方", 
    "floor": "9082", 
    "url": "http://jandan.net/duan/page-364#comment-2781737", 
    "against": "2", 
    "content": "一百块到底有多值钱并不取决于通货膨胀，而取决于花钱当天是月初还是月末。"
  }, 
  {
    "zan": "82", 
    "publish_time": "@10 MONTHS AGO", 
    "auther": "光消失的地方", 
    "floor": "9081", 
    "url": "http://jandan.net/duan/page-364#comment-2781736", 
    "against": "2", 
    "content": "念念不忘，必会下单。"
  }, 
  {
    "zan": "26", 
    "publish_time": "@10 MONTHS AGO", 
    "auther": "光消失的地方", 
    "floor": "9080", 
    "url": "http://jandan.net/duan/page-364#comment-2781735", 
    "against": "4", 
    "content": "真金不怕火炼，怕你没钱。"
  }, 
  {
    "zan": "60", 
    "publish_time": "@10 MONTHS AGO", 
    "auther": "光消失的地方", 
    "floor": "9079", 
    "url": "http://jandan.net/duan/page-364#comment-2781733", 
    "against": "15", 
    "content": "“可笑的是，我们总以为爱对了是爱情，爱错了就是邂逅。然而对错哪有那么容易分得清，无非时间作祟。可时间过得越久，对错也就越不重要。只要愿意坚持，一切都是对的。”"
  }, 
  {
    "zan": "41", 
    "publish_time": "@10 MONTHS AGO", 
    "auther": "光消失的地方", 
    "floor": "9078", 
    "url": "http://jandan.net/duan/page-364#comment-2781729", 
    "against": "3", 
    "content": "我有两个梦想：1、睡觉能减肥。2、能睡上一个星期。"
  }, 
  {
    "zan": "146", 
    "publish_time": "@10 MONTHS AGO", 
    "auther": "Xavier", 
    "floor": "9077", 
    "url": "http://jandan.net/duan/page-364#comment-2781724", 
    "against": "9", 
    "content": "越野车看见大卡车倒在路边，便上去询问，大卡车说：“今天碰到一个可爱的小跑车…”　　“撞上了？”　　“不，被她萌翻了。 ”"
  }, 
  {
    "zan": "97", 
    "publish_time": "@10 MONTHS AGO", 
    "auther": "Xavier", 
    "floor": "9076", 
    "url": "http://jandan.net/duan/page-364#comment-2781720", 
    "against": "9", 
    "content": "妈妈教育我：“你可不要被女人给骗了，女人的话你别信。 ”　　一时之间我竟不知道该不该听妈妈的话。"
  }, 
  {
    "zan": "171", 
    "publish_time": "@10 MONTHS AGO", 
    "auther": "光消失的地方", 
    "floor": "9075", 
    "url": "http://jandan.net/duan/page-364#comment-2781712", 
    "against": "39", 
    "content": "她和他分手，说不甘心这辈子只和一个平庸男人一起。他黯然去别城打拼，十年后事业有成，依然爱她。也听说她嫁给有钱人生活安逸但不快乐。后来他被邀请参加同学聚会，知道她也来他故意穿得落魄潦倒，有人奇怪，他说：我要让她相信当年抛弃我的选择是正确的，这样她现在会感觉幸福一点。"
  }
]