[
  {
    "zan": "209", 
    "publish_time": "@1 YEAR AGO", 
    "auther": "木头", 
    "floor": "5549", 
    "url": "http://jandan.net/duan/page-222#comment-2694615", 
    "against": "25", 
    "content": "晚上和老婆回家，突然从旁边跳出三个持刀蒙面抢劫犯，说：“你俩其中一个可以走”。我猛然就把我老婆推到一边：“老婆你快走”。\n待老婆消失后，三个蒙面人脱下面具说：“我去尼玛的，现在找你打个麻将都得这么费劲了！？”\n五分钟后我致电老婆：＂往xxxxxxxx＂卡里打五千块，一帮小贼，要的不多。咱花钱免灾吧，千万别报警，几个大哥说了，关我一夜，明早就放人。＂十分钟后，我从卡里支出老婆打来的五千块战斗到天明。\n小胜五百疲惫归家，老婆一夜提心吊胆，赶紧给我熬粥做菜并深情含泪说：“老公，关键时候看出你对我的好，以后你吃啥我就都给你做。”"
  }, 
  {
    "zan": "243", 
    "publish_time": "@1 YEAR AGO", 
    "auther": "光消失的地方", 
    "floor": "5548", 
    "url": "http://jandan.net/duan/page-222#comment-2694600", 
    "against": "5", 
    "content": "我爹从小教育我，不能让一个女人哭，因为女人的眼泪是她脑子里面进的水，脑子里面进的水要是流干的话，以后可就不好对付了"
  }, 
  {
    "zan": "34", 
    "publish_time": "@1 YEAR AGO", 
    "auther": "冷饭头盔", 
    "floor": "5547", 
    "url": "http://jandan.net/duan/page-222#comment-2694586", 
    "against": "35", 
    "content": "像  人越胖jj越小 这样的神论还有吗"
  }, 
  {
    "zan": "24", 
    "publish_time": "@1 YEAR AGO", 
    "auther": "大菠萝菜", 
    "floor": "5546", 
    "url": "http://jandan.net/duan/page-222#comment-2694554", 
    "against": "6", 
    "content": "女子篮球在我国具有悠久的历史，啊？要证据？你看看古装电视，搭彩楼抛绣球的大家闺秀都能砸到如意郎君这就是证据。"
  }, 
  {
    "zan": "51", 
    "publish_time": "@1 YEAR AGO", 
    "auther": "麦林炮手", 
    "floor": "5545", 
    "url": "http://jandan.net/duan/page-222#comment-2694516", 
    "against": "131", 
    "content": "有一天我很饿，所以吃了很多饭，然后吃饱了"
  }, 
  {
    "zan": "148", 
    "publish_time": "@1 YEAR AGO", 
    "auther": "foreveralone", 
    "floor": "5544", 
    "url": "http://jandan.net/duan/page-222#comment-2694485", 
    "against": "67", 
    "content": "他的姓氏以”江”开头，经常戴着一副黑框眼镜 。他和一个年龄相差悬殊的女人保持了十几年的不正常关系。他姿势水平很高，和记者朋友官府要员谈笑风生。他和一个姓毛的人从事相同的工作，因他而死的人数不胜数。现在的他虽然退居二线，但发生事端时，他依旧垂帘听政，幕后操作。谣言曾说他已去世，他也渐渐被世人淡忘，如今也只有少数几人知道他是否还活着。他，就是江户川柯南。"
  }, 
  {
    "zan": "224", 
    "publish_time": "@1 YEAR AGO", 
    "auther": "光消失的地方", 
    "floor": "5543", 
    "url": "http://jandan.net/duan/page-222#comment-2694418", 
    "against": "26", 
    "content": "晚上逛贴吧看到个技术贴，用修改器看仙剑dos的各项数据，看到援护那里，李逍遥可援护三女主，而援护李逍遥的只有林月如。。。小时候因为林月如挡刀不至于丢了数小时进度，而开始留心喜欢她，二十年未变。原来所有人里，能为他挡下一刀一剑的只有这一个人，只有一人。虽然是到了今天才知道。"
  }, 
  {
    "zan": "182", 
    "publish_time": "@1 YEAR AGO", 
    "auther": "自寻箱子", 
    "floor": "5542", 
    "url": "http://jandan.net/duan/page-222#comment-2694312", 
    "against": "7", 
    "content": "和二货同学去买耳麦～二货戴上以后拿下来看着耳麦左边的大写 L 对老板说：L的太大！给我换个M的！！LZ立即转身离开表示不认识他……"
  }, 
  {
    "zan": "371", 
    "publish_time": "@1 YEAR AGO", 
    "auther": "自寻箱子", 
    "floor": "5541", 
    "url": "http://jandan.net/duan/page-222#comment-2694311", 
    "against": "11", 
    "content": "昨天隔壁老头的追悼会开了，会上宣读了老头的遗言：遗产不分，作为基金，每年取出利息，在墓前每年家人团聚一次，祭拜之后进行抽奖……"
  }, 
  {
    "zan": "230", 
    "publish_time": "@1 YEAR AGO", 
    "auther": "光消失的地方", 
    "floor": "5540", 
    "url": "http://jandan.net/duan/page-222#comment-2694290", 
    "against": "12", 
    "content": "电梯里，一中年男人紧盯一妙龄女子，女子生气的说“老不正经，” 男人正色道“姑娘，你想多了，我女儿都和你差不多大了，” 女子脸一红“对不起，大爷，” 中年男人“没关系，约吗…？”"
  }, 
  {
    "zan": "345", 
    "publish_time": "@1 YEAR AGO", 
    "auther": "光消失的地方", 
    "floor": "5539", 
    "url": "http://jandan.net/duan/page-222#comment-2694289", 
    "against": "3", 
    "content": "我是个通下水道的，今天有人打电话去给一户通便池时，通出了好多TT，我就跟男户主说，以后用过的TT不要扔马捅里冲，容易打结，给堵上。我刚说完，男户主转身就合女户主打起来了，我应该怎么去劝架，关建是没给我钱，都快过年了，我也不容易"
  }, 
  {
    "zan": "301", 
    "publish_time": "@1 YEAR AGO", 
    "auther": "光消失的地方", 
    "floor": "5538", 
    "url": "http://jandan.net/duan/page-222#comment-2694287", 
    "against": "4", 
    "content": "初中的时候喜欢一个男生，有一次他被几个人打了，之后他颓废的坐在操场的篮球架下，我便出去买些药水给他擦擦。但他始终不知道是我叫我哥打他的。"
  }, 
  {
    "zan": "390", 
    "publish_time": "@1 YEAR AGO", 
    "auther": "光消失的地方", 
    "floor": "5537", 
    "url": "http://jandan.net/duan/page-222#comment-2694286", 
    "against": "7", 
    "content": "公交车上，刚上车就看到一对情侣，我走上前对那男的说“我怀孕了！”那男的惊呆的看着我，那女的也瞪大眼镜看着我，空气瞬间凝固了三秒钟，然后那女的“啪”的给那男的一巴掌。我继续说“让个位呗！”"
  }, 
  {
    "zan": "66", 
    "publish_time": "@1 YEAR AGO", 
    "auther": "光消失的地方", 
    "floor": "5536", 
    "url": "http://jandan.net/duan/page-222#comment-2694283", 
    "against": "4", 
    "content": "闺密：“昨晚我做梦梦到男神了” 我：“梦都是相反的” 闺密：“你是说男神也梦到我了？”"
  }, 
  {
    "zan": "116", 
    "publish_time": "@1 YEAR AGO", 
    "auther": "好色猴子", 
    "floor": "5535", 
    "url": "http://jandan.net/duan/page-222#comment-2694273", 
    "against": "2", 
    "content": "@碧格朗菲斯：不喜欢有人坐得靠我太近，怕他们压到我隐形的翅膀\n@所长别开枪是我：你姨妈巾的护翼太长了吧…"
  }, 
  {
    "zan": "208", 
    "publish_time": "@1 YEAR AGO", 
    "auther": "leemonuu", 
    "floor": "5534", 
    "url": "http://jandan.net/duan/page-222#comment-2694271", 
    "against": "63", 
    "content": "听盆友说的，一位48岁的大叔脑干出血在监护室，大妈在外哭的止不住，电话来了，这位大妈马上不哭了，接过电话对在新疆工作的儿子微笑的说你老爸没事，就是吃的不合适胃疼好儿子你在外面好好工作。挂了电话大妈瘫倒在医院的走廊。瞬间我也泪流满面。"
  }, 
  {
    "zan": "59", 
    "publish_time": "@1 YEAR AGO", 
    "auther": "L", 
    "floor": "5533", 
    "url": "http://jandan.net/duan/page-222#comment-2694246", 
    "against": "6", 
    "content": "情人节已经过了 别再发情人系列了 好吗？ 不然残血的单身狗哪里有hp抗住迎面而来新年拷问和元宵寂寞啊！"
  }, 
  {
    "zan": "83", 
    "publish_time": "@1 YEAR AGO", 
    "auther": "maylog", 
    "floor": "5532", 
    "url": "http://jandan.net/duan/page-222#comment-2694211", 
    "against": "17", 
    "content": "昨天有人问我如何跟女朋友永不分离，我回答在啪啪啪的时候，把润滑油换成502就可以了#我真是天才"
  }, 
  {
    "zan": "13", 
    "publish_time": "@1 YEAR AGO", 
    "auther": "maylog", 
    "floor": "5531", 
    "url": "http://jandan.net/duan/page-222#comment-2694188", 
    "against": "28", 
    "content": "看了裸飞的几十分钟 “我就是有钱女人倒贴上来我玩完就甩跪着求我我都不要” 式的自我剖析 感觉灵魂得到了升华…"
  }, 
  {
    "zan": "292", 
    "publish_time": "@1 YEAR AGO", 
    "auther": "maylog", 
    "floor": "5530", 
    "url": "http://jandan.net/duan/page-222#comment-2694186", 
    "against": "16", 
    "content": "有人问:什么叫蝴蝶效应啊？\n一帅哥去吃刀削面，\n服务员问要大碗要小碗，\n他说小碗。\n发现没吃饱，\n就去饭店又要了个菜，\n刚好碰到熟人，\n喝了点酒，\n熟人非要拉着去嫖娼，\n警察来了。\n因为这事，\n单位开除了，\n老婆离婚。\n问他心里什么想法？\n帅哥说：当时要个大碗的就没事了！"
  }, 
  {
    "zan": "115", 
    "publish_time": "@1 YEAR AGO", 
    "auther": "maylog", 
    "floor": "5529", 
    "url": "http://jandan.net/duan/page-222#comment-2694133", 
    "against": "49", 
    "content": "宜宾机场已改名为五粮液机场。可以预想不久的将来，您登机前会听到这样的通知：由五粮液机场前往二锅头国际机场的旅客请注意！您所乘坐的老白干航班已经到达本站，请携带好您随身物品到酒鬼登机口登机，在国窖1573口排队等候！由于闷倒驴机场天气原因，小刀烧航班取消，请旅客们改乘劲酒航班…"
  }, 
  {
    "zan": "114", 
    "publish_time": "@1 YEAR AGO", 
    "auther": "maylog", 
    "floor": "5528", 
    "url": "http://jandan.net/duan/page-222#comment-2694130", 
    "against": "8", 
    "content": "某博士生发推说：隔壁实验室教授的小女儿刚上幼儿园，不想上学，现在终于放寒假了，问她爸爸：我什么时候才能不用再上学。。。教授看了我一眼，我默默流下眼泪"
  }, 
  {
    "zan": "123", 
    "publish_time": "@1 YEAR AGO", 
    "auther": "maylog", 
    "floor": "5527", 
    "url": "http://jandan.net/duan/page-222#comment-2694111", 
    "against": "16", 
    "content": "他身家千万，拥有豪车无数，私家豪华餐厅，现代化农牧场。自从QQ号丢了以后，他就一无所有了。。"
  }, 
  {
    "zan": "53", 
    "publish_time": "@1 YEAR AGO", 
    "auther": "光消失的地方", 
    "floor": "5526", 
    "url": "http://jandan.net/duan/page-222#comment-2694110", 
    "against": "16", 
    "content": "老崔指着一个老头对我说，他是守自行车的，一个月挣两千来块，但是他每个月都给残疾人、孤寡老人、孤儿捐钱，至少捐一千。我惊呆了：这么好的人，你们成都的电视台为什么不报道。老崔说，很正常，成都这种人很多，我就认识十几个。“他们通过什么渠道捐助呢？”我问。“中国福利彩票。”"
  }, 
  {
    "zan": "31", 
    "publish_time": "@1 YEAR AGO", 
    "auther": "光消失的地方", 
    "floor": "5525", 
    "url": "http://jandan.net/duan/page-222#comment-2694109", 
    "against": "43", 
    "content": "公司年会上做填字游戏， 有一道题目是五（ ）四（ ）， 大家把答案写好投进答题箱， 主持人边抽边念，大多数的人填的是五（湖）四（海），五（书）四（经）等。 最奇葩的答案是五（八）四（十）。 主持人怒道：“谁数学这么好？”"
  }
]