[
  {
    "zan": "57", 
    "publish_time": "@4 MONTHS AGO", 
    "auther": "光消失的地方", 
    "floor": "17024", 
    "url": "http://jandan.net/duan/page-681#comment-2959385", 
    "against": "8", 
    "content": "一女同事交男朋友就一个条件就是“必须手小”。 那天我问他为啥？ 她答：“那样他就不会感觉我的胸小了！” 好有道理。。。。"
  }, 
  {
    "zan": "47", 
    "publish_time": "@4 MONTHS AGO", 
    "auther": "moon", 
    "floor": "17023", 
    "url": "http://jandan.net/duan/page-681#comment-2959347", 
    "against": "22", 
    "content": "科学家发现，可以从指纹判断出一个人是白人还是黑人。 详细说来是这样的：如果你的指纹是在犯案现场被找到的，那你八成是个黑人。——manxman"
  }, 
  {
    "zan": "33", 
    "publish_time": "@4 MONTHS AGO", 
    "auther": "李", 
    "floor": "17022", 
    "url": "http://jandan.net/duan/page-681#comment-2959344", 
    "against": "8", 
    "content": "早晨吃饱后，不能一上班就去厕所，因为出来时容易打嗝"
  }, 
  {
    "zan": "12", 
    "publish_time": "@4 MONTHS AGO", 
    "auther": "谋杀在黑夜", 
    "floor": "17021", 
    "url": "http://jandan.net/duan/page-681#comment-2959332", 
    "against": "87", 
    "content": "在云南叫了个Uber，一头大象就duang~duang~duang~ 的到我面前了，栓在宿舍楼下的大象不小心吃了点被人掉的冰毒，被砍了30多刀，现在都爬着送我去上课！"
  }, 
  {
    "zan": "8", 
    "publish_time": "@4 MONTHS AGO", 
    "auther": "众人皆醒", 
    "floor": "17020", 
    "url": "http://jandan.net/duan/page-681#comment-2959291", 
    "against": "100", 
    "content": "“人生得意须尽欢，莫使金樽空对月。来，满上！”李白指着酒杯对众人说道。"
  }, 
  {
    "zan": "37", 
    "publish_time": "@4 MONTHS AGO", 
    "auther": "派小星", 
    "floor": "17019", 
    "url": "http://jandan.net/duan/page-681#comment-2959253", 
    "against": "15", 
    "content": "可爱的四川同学初到美帝，由于之前套磁全靠电邮来往因此在orientation上需要靠导师的胸牌才能认出自己的大boss，终于找到之后她激动不已冲上前对导师说：“hello！I know your name！”\n导师一脸诧异的说：“you know I’m lame?”"
  }, 
  {
    "zan": "105", 
    "publish_time": "@4 MONTHS AGO", 
    "auther": "moon", 
    "floor": "17018", 
    "url": "http://jandan.net/duan/page-681#comment-2959242", 
    "against": "4", 
    "content": "酒吧里跟人起了冲突，我怒踹对方一脚，问道：”你知道我爸是谁吗？”\n对方当时有点吓住了，说：“不知道。”\n“我也不知道，我是个孤儿，呜呜呜呜。”"
  }, 
  {
    "zan": "35", 
    "publish_time": "@4 MONTHS AGO", 
    "auther": "moon", 
    "floor": "17017", 
    "url": "http://jandan.net/duan/page-681#comment-2959241", 
    "against": "5", 
    "content": "老师上课讲到，伟大数学家也有误区，所以你们注意别较真，容易进误区。旁边学渣幽幽的来了一句，我数学从未有误区。我一脸惊讶。那二货补充到，我从来只有盲区。。"
  }, 
  {
    "zan": "178", 
    "publish_time": "@4 MONTHS AGO", 
    "auther": "moon", 
    "floor": "17016", 
    "url": "http://jandan.net/duan/page-681#comment-2959236", 
    "against": "11", 
    "content": "刚到单位一女的上来就是给我一嘴巴子，“你打我干嘛啊！”\n“我呸，你昨晚上在我梦里做那点破事你不知道吗？”\n我。。。"
  }, 
  {
    "zan": "60", 
    "publish_time": "@4 MONTHS AGO", 
    "auther": "gemei", 
    "floor": "17015", 
    "url": "http://jandan.net/duan/page-681#comment-2959232", 
    "against": "6", 
    "content": "刚结婚的时候老妈不会做饭，老爸做得一手好菜，然后老爸就假意教学，并且不管多难吃都大加赞赏。终于教会了，老爸就甩手掌柜的了。"
  }, 
  {
    "zan": "11", 
    "publish_time": "@4 MONTHS AGO", 
    "auther": "不吃鱼的狼", 
    "floor": "17014", 
    "url": "http://jandan.net/duan/page-681#comment-2959213", 
    "against": "37", 
    "content": "翻过全身上下，屋里的每个角落，只剩下五元钱了！还有比这更痛苦的吗？\n…………………………\n有，比如被偷了。"
  }, 
  {
    "zan": "215", 
    "publish_time": "@4 MONTHS AGO", 
    "auther": "夜赏销魂曲", 
    "floor": "17013", 
    "url": "http://jandan.net/duan/page-681#comment-2959210", 
    "against": "17", 
    "content": "她说：分手吧！他说：好。他说，走一百步吧，以后见面还是朋友。”她忍着心痛走了99步，最后一步她回头了却一头撞在他的怀里。 她愣住了！ 他平静地说：“只要你肯回头，我会一直在你身后” 她哭得泣不成声，而他也顺势扔开了藏在背后的板砖。"
  }, 
  {
    "zan": "7", 
    "publish_time": "@4 MONTHS AGO", 
    "auther": "不吃鱼的狼", 
    "floor": "17012", 
    "url": "http://jandan.net/duan/page-681#comment-2959196", 
    "against": "26", 
    "content": "翻过全身上下，屋里的每个角落，只剩下五元钱了！还有比这更痛苦的吗？\n…………………………\n有，比如被偷了。"
  }, 
  {
    "zan": "94", 
    "publish_time": "@4 MONTHS AGO", 
    "auther": "光消失的地方", 
    "floor": "17011", 
    "url": "http://jandan.net/duan/page-681#comment-2959138", 
    "against": "10", 
    "content": "我们对年龄的恐惧，其实并不在于年龄增长所带来的苍老，而是恐惧随着年龄的增长，我们仍然一无所得。"
  }, 
  {
    "zan": "48", 
    "publish_time": "@4 MONTHS AGO", 
    "auther": "光消失的地方", 
    "floor": "17010", 
    "url": "http://jandan.net/duan/page-681#comment-2959132", 
    "against": "4", 
    "content": "最难的不是做选择，而是承担后果。"
  }, 
  {
    "zan": "17", 
    "publish_time": "@4 MONTHS AGO", 
    "auther": "你阿妈大减价", 
    "floor": "17009", 
    "url": "http://jandan.net/duan/page-681#comment-2959127", 
    "against": "98", 
    "content": "今天上班，领导对我说：“世界那么大，你就不想去看看？” 心里一惊！我擦，这是炒鱿鱼的新词么？ 我稳稳的回答：领导，您就是我的世界！ 领导笑着说“你哪里都不去么？”我坚决表态“领导放心，公司是我家，我哪儿都不去”。 领导说“可惜，这次组织大家到马尔代夫玩，既然你这样说，那么你就留在公司值班吧！”"
  }, 
  {
    "zan": "31", 
    "publish_time": "@4 MONTHS AGO", 
    "auther": "Atlas", 
    "floor": "17008", 
    "url": "http://jandan.net/duan/page-681#comment-2959111", 
    "against": "26", 
    "content": "常驻煎蛋的我其实并不会做煎鸡蛋"
  }, 
  {
    "zan": "60", 
    "publish_time": "@4 MONTHS AGO", 
    "auther": "HSJ", 
    "floor": "17007", 
    "url": "http://jandan.net/duan/page-681#comment-2959108", 
    "against": "3", 
    "content": "前国脚郝海东再度做客《郝大炮》节目。节目中，郝海东爆料年轻时曾在公交车上遭到同性骚扰。“当年我们88年打联赛呢，我和江洪坐公交车出去，旁边就坐着个穿背带裤的男的，过来直摸我。哎呦，你是运动员吧，身体真好。江洪坐了一站告诉我，海东，咱赶紧走吧！当年姜峰少年队时候也遇到过这事儿呢，有沙特的还是中东的球员要把他弄到酒店那什么。”"
  }, 
  {
    "zan": "56", 
    "publish_time": "@4 MONTHS AGO", 
    "auther": "我想养猪", 
    "floor": "17006", 
    "url": "http://jandan.net/duan/page-681#comment-2959080", 
    "against": "39", 
    "content": "地球OL之人类\n简易模式:欧美日\n中等模式:中俄\n困难模式:拉非\n地狱模式:中东"
  }, 
  {
    "zan": "178", 
    "publish_time": "@4 MONTHS AGO", 
    "auther": "光消失的地方", 
    "floor": "17005", 
    "url": "http://jandan.net/duan/page-681#comment-2959074", 
    "against": "7", 
    "content": "今天晚上去公园夜跑，有一对情侣估计想野战，我就绕着公园各个角落跑，结果我跑了10km，他们躲了1小时，最后10点一起被安保清场！"
  }, 
  {
    "zan": "97", 
    "publish_time": "@4 MONTHS AGO", 
    "auther": "光消失的地方", 
    "floor": "17004", 
    "url": "http://jandan.net/duan/page-681#comment-2959073", 
    "against": "3", 
    "content": "今天去剪头发，理发师很安静的给我里完了发，并没有想象中的各种推销办卡，回寝室跟同学说了后，同学说“人家一看你就是个穷B，懒得跟你废话”… –"
  }, 
  {
    "zan": "73", 
    "publish_time": "@4 MONTHS AGO", 
    "auther": "光消失的地方", 
    "floor": "17003", 
    "url": "http://jandan.net/duan/page-681#comment-2959072", 
    "against": "7", 
    "content": "设计师过劳死后，鬼魂会被困在自己生前的座位上不停改改改改改改改，不得超生。只有求得其生前甲方的签字立誓不改了，也不用第一稿的血书，还有已经付款的合同，然后一起做法事烧掉，才能将其超度"
  }, 
  {
    "zan": "57", 
    "publish_time": "@4 MONTHS AGO", 
    "auther": "光消失的地方", 
    "floor": "17002", 
    "url": "http://jandan.net/duan/page-681#comment-2959071", 
    "against": "8", 
    "content": "婚前老婆曾对我说：我这人缺点很多，但是至少有两个优点，一是勤快，二是功夫好。听到第二点我想都没想就与她结了婚，直到婚后经常被她打得鼻青脸肿我才明白，原来她真的是功夫好！"
  }, 
  {
    "zan": "114", 
    "publish_time": "@4 MONTHS AGO", 
    "auther": "光消失的地方", 
    "floor": "17001", 
    "url": "http://jandan.net/duan/page-681#comment-2959069", 
    "against": "5", 
    "content": "海底捞服务员可以进入我最害怕的人前五名，无处不在的窥视和体察入微的关怀足以逼疯一个社交恐惧症患者。对，他们还会坚持给你唱生日快乐歌，拦都拦不住，一个大写的尴尬。"
  }, 
  {
    "zan": "77", 
    "publish_time": "@4 MONTHS AGO", 
    "auther": "光消失的地方", 
    "floor": "17000", 
    "url": "http://jandan.net/duan/page-681#comment-2959068", 
    "against": "5", 
    "content": "所以每次看见什么“超人可以一巴掌呼死蝙蝠侠”的，真的是很悲伤，按照设定你也可以一巴掌呼死你的猫，为什么还要跪下铲屎"
  }
]