[
  {
    "zan": "246", 
    "publish_time": "@3 WEEKS AGO", 
    "auther": "maylog", 
    "floor": "22249", 
    "url": "http://jandan.net/duan/page-890#comment-3052538", 
    "against": "3", 
    "content": "一男子持枪闯进了一家酒吧。谁他妈的睡了我老婆？他吼道。角落里一个低沉的声音回答道：哥们，你那一梭子子弹可不够。 #译自英语推"
  }, 
  {
    "zan": "232", 
    "publish_time": "@3 WEEKS AGO", 
    "auther": "Utopia", 
    "floor": "22248", 
    "url": "http://jandan.net/duan/page-890#comment-3052529", 
    "against": "3", 
    "content": "“儿砸！过年不要顾着玩手机，和叔叔阿姨说说话嘛。”\n“说些什么啊？没什么好说的啊。”\n“你就随便说说，说些大家都懂的。”“阿姨，你听说过安利吗？”"
  }, 
  {
    "zan": "121", 
    "publish_time": "@3 WEEKS AGO", 
    "auther": "maylog", 
    "floor": "22247", 
    "url": "http://jandan.net/duan/page-890#comment-3052479", 
    "against": "23", 
    "content": "当女朋友因为要来大姨妈烦躁的时候，男人就应该紧紧抱住她，说：“我真没用，还让你来大姨妈”。。"
  }, 
  {
    "zan": "306", 
    "publish_time": "@3 WEEKS AGO", 
    "auther": "快乐精品秀", 
    "floor": "22246", 
    "url": "http://jandan.net/duan/page-890#comment-3052473", 
    "against": "13", 
    "content": "一张手纸只有10%的面积是用来擦屎的，剩下90%的面积是为了防止手沾到屎。你的投资生涯应该只有10%的时间是做交易的，剩下90%的时间是用来思考保证交易不出错。"
  }, 
  {
    "zan": "191", 
    "publish_time": "@3 WEEKS AGO", 
    "auther": "快乐精品秀", 
    "floor": "22245", 
    "url": "http://jandan.net/duan/page-890#comment-3052455", 
    "against": "3", 
    "content": "最近微信加了个妹子,看她发来的照片长的还不错,就夸她长的漂亮,她说,这年代,美图秀秀有多厉害你又不是不知道.我看她这么谦虚,对她好感大增,后来彼此了解深入,提出了见面,然后,我们见面了,再然后,我就知道了美图秀秀究竟有多强大….."
  }, 
  {
    "zan": "61", 
    "publish_time": "@3 WEEKS AGO", 
    "auther": "光消失的地方", 
    "floor": "22244", 
    "url": "http://jandan.net/duan/page-890#comment-3052403", 
    "against": "11", 
    "content": "“雨夹雪，雪会疼吗？雷震雨，雨会痛吗？”"
  }, 
  {
    "zan": "51", 
    "publish_time": "@3 WEEKS AGO", 
    "auther": "光消失的地方", 
    "floor": "22243", 
    "url": "http://jandan.net/duan/page-890#comment-3052402", 
    "against": "134", 
    "content": "“死者女，31岁，单身，被刺19刀，并且脸部被毁容。”\n“太可怕了。”\n“的确，凶手不但杀人还毁容，应该是有变态心理。”\n“我是说31岁还单身，可怕。。。”"
  }, 
  {
    "zan": "130", 
    "publish_time": "@3 WEEKS AGO", 
    "auther": "光消失的地方", 
    "floor": "22242", 
    "url": "http://jandan.net/duan/page-890#comment-3052401", 
    "against": "8", 
    "content": "我还是放弃了参加今年的“快男”，可能我太迷信了吧，总觉得那俩字儿挺晦气的。"
  }, 
  {
    "zan": "171", 
    "publish_time": "@3 WEEKS AGO", 
    "auther": "光消失的地方", 
    "floor": "22241", 
    "url": "http://jandan.net/duan/page-890#comment-3052400", 
    "against": "11", 
    "content": "第一次带女朋友回家，母亲煮了一锅自家种植的香米。那饭特别好吃。 女朋友胃口本来就好，第一次吃那种米饭，刹不住车了。马上风展残云干掉了4碗。见她意犹未尽，我眼神示意她放碗，没想到被机敏的母亲觉察，她马上说：快给姑娘盛饭，没啥菜，还不让人吃饱饭咋的？！ 结果，那二货也真不客气，结结实实干掉了6碗！事后，母亲神情凝重地对我说：儿呀，妹子其它的都好，就你那点点工资，恐怕养不活她啊！ ……"
  }, 
  {
    "zan": "98", 
    "publish_time": "@3 WEEKS AGO", 
    "auther": "光消失的地方", 
    "floor": "22240", 
    "url": "http://jandan.net/duan/page-890#comment-3052398", 
    "against": "6", 
    "content": "看到一对小情侣在吵架，那男的竟然动手打他女朋友，我实在看不下去了，就把望远镜对向另外一个窗户。"
  }, 
  {
    "zan": "45", 
    "publish_time": "@3 WEEKS AGO", 
    "auther": "光消失的地方", 
    "floor": "22239", 
    "url": "http://jandan.net/duan/page-890#comment-3052392", 
    "against": "7", 
    "content": "我这个人对去吃饭的餐厅要求是很高的，只要没有wifi我肯定扭头就走。"
  }, 
  {
    "zan": "86", 
    "publish_time": "@3 WEEKS AGO", 
    "auther": "光消失的地方", 
    "floor": "22238", 
    "url": "http://jandan.net/duan/page-890#comment-3052391", 
    "against": "5", 
    "content": "多年后她在电视上看到年轻时喜欢的偶像，不禁湿了眼眶，转头对着身边的儿子说:“儿子，知道为什么妈妈哭吗？”儿子沉默:“……”她微笑着摸摸儿子的头:“这个人是妈妈的青春哦，差点就成了你爸爸呢。”儿子的视线没有离开电视，嗑着瓜子道:“妈，前几天你看到其他频道几个叔叔的时候，也是这么说的。”"
  }, 
  {
    "zan": "88", 
    "publish_time": "@3 WEEKS AGO", 
    "auther": "光消失的地方", 
    "floor": "22237", 
    "url": "http://jandan.net/duan/page-890#comment-3052387", 
    "against": "6", 
    "content": "最厉害的人 就是那种 说起床就起床 说学习就学习 说玩就玩 说睡觉就睡觉的人。而我就是第四种人。"
  }, 
  {
    "zan": "203", 
    "publish_time": "@3 WEEKS AGO", 
    "auther": "好色猴子", 
    "floor": "22236", 
    "url": "http://jandan.net/duan/page-890#comment-3052348", 
    "against": "16", 
    "content": "我弟特别喜欢周杰伦，通讯录里都是用的周杰伦的歌名做备注。比如给老爸的备注是“以父之名”，给老妈的是“听妈妈的话”，给他女朋友备注的是“可爱女人”。我很好奇他给我备注的是啥，就去翻了下他的手机，发现他给我的备注是：\n印第安老斑鸠"
  }, 
  {
    "zan": "308", 
    "publish_time": "@3 WEEKS AGO", 
    "auther": "缝衣付与溧", 
    "floor": "22235", 
    "url": "http://jandan.net/duan/page-890#comment-3052338", 
    "against": "14", 
    "content": "“我爱你。” “我也爱你。”\n“可我已经结婚了。”“没关系。”\n“而且我还有小孩了。”“也没关系。”\n“为什么这样爱我？”“因为……我也结婚了。”\n“哦天啦！”“我也有孩子了。”“哦不!”\n这时进来一个小孩说：“别玩了，爸，妈。该起床了。”"
  }, 
  {
    "zan": "130", 
    "publish_time": "@3 WEEKS AGO", 
    "auther": "缝衣付与溧", 
    "floor": "22234", 
    "url": "http://jandan.net/duan/page-890#comment-3052336", 
    "against": "21", 
    "content": "”疼吗？”\n”疼”\n“还要继续吗？”\n“继续。”\n“流了好多血哎！”\n“没关系。”\n“关将军果然神勇。”\n>华佗如是说！"
  }, 
  {
    "zan": "154", 
    "publish_time": "@3 WEEKS AGO", 
    "auther": "Xavier", 
    "floor": "22233", 
    "url": "http://jandan.net/duan/page-890#comment-3052331", 
    "against": "10", 
    "content": "听老人的忠告，不是因为他们都是对的，而是因为他们走弯路的经验丰富。"
  }, 
  {
    "zan": "54", 
    "publish_time": "@3 WEEKS AGO", 
    "auther": "缝衣付与溧", 
    "floor": "22232", 
    "url": "http://jandan.net/duan/page-890#comment-3052328", 
    "against": "130", 
    "content": "1.亲爱的，今天有个富二代跟我表白了耶。我答应了。\n2.我跟你在一起三年多了，连个像样的房子都租不起。不如我去给他泡几个月，换一套房子来我们住，怎么样？\n3.哈哈，看看你的表情。我骗你的啦。其实，我答应他，是因为真心喜欢他。\n4.别难过，我不会丢下你的，我们三个可以一起啊。他跟我说，他也很喜欢小猫的。(via @沐亚人)"
  }, 
  {
    "zan": "160", 
    "publish_time": "@3 WEEKS AGO", 
    "auther": "缝衣付与溧", 
    "floor": "22231", 
    "url": "http://jandan.net/duan/page-890#comment-3052326", 
    "against": "90", 
    "content": "我喜欢吃苹果，男友会削两个，一 人一个。 我喜欢这温馨浪漫的感觉。只是发现男友总是先把两个苹果各咬一口再递给我。我觉得很奇怪，终于有一天，趁男友出去接电话时，我拿过男友的苹果咬了一口，感觉不如自己的脆甜可口。 原来，他总是把最好的留给我，瞬间泪水无声滑过脸庞，这么好的男人为什么偏偏硬不起来？……还好我能硬。(via @zhihu卓恒)"
  }, 
  {
    "zan": "375", 
    "publish_time": "@3 WEEKS AGO", 
    "auther": "光消失的地方", 
    "floor": "22230", 
    "url": "http://jandan.net/duan/page-890#comment-3052243", 
    "against": "5", 
    "content": "相亲时，我和对方简单地介绍了一下自己，我：“我不缺钱，但我喜欢坦诚的女人。你呢？”\n女：“我愿意嫁你这个丑B。”"
  }, 
  {
    "zan": "159", 
    "publish_time": "@3 WEEKS AGO", 
    "auther": "天朝特使", 
    "floor": "22229", 
    "url": "http://jandan.net/duan/page-890#comment-3052196", 
    "against": "19", 
    "content": "老公出去了今晚一个人在家，隔壁王大哥敲门说来蹭个wife，我家没装wife啊？"
  }, 
  {
    "zan": "72", 
    "publish_time": "@3 WEEKS AGO", 
    "auther": "glare", 
    "floor": "22228", 
    "url": "http://jandan.net/duan/page-890#comment-3052195", 
    "against": "7", 
    "content": "人最痛苦的三件事：吃不下，拉不出，尿不尽。\n更痛苦的三件事：做胃镜，做肠镜，尿道手术。"
  }, 
  {
    "zan": "43", 
    "publish_time": "@3 WEEKS AGO", 
    "auther": "天朝特使", 
    "floor": "22227", 
    "url": "http://jandan.net/duan/page-890#comment-3052178", 
    "against": "73", 
    "content": "今天起来，我竟发现我和我好友的男友睡在一张床上，起来我俩还浑身都很疼，床单上还有血，不知怎么回事……我唯一知道的是昨天晚上喝了酒我女票和我好友先走了，好友的男票送我回家……"
  }, 
  {
    "zan": "39", 
    "publish_time": "@3 WEEKS AGO", 
    "auther": "天朝特使", 
    "floor": "22226", 
    "url": "http://jandan.net/duan/page-890#comment-3052174", 
    "against": "137", 
    "content": "伟大领袖发话了：“在火箭技术上，我们要领先美国，所以，火箭的质量必须是美国的两倍！”技术人员拍着胸脯：“保证完成任务！”火箭发射时，爆炸了。伟大领袖大怒：“这是怎么回事？”技术人员：“您说的啊，火箭的质量必须是美国的两倍，那么重就飞不起来，自然就爆了！”"
  }, 
  {
    "zan": "271", 
    "publish_time": "@3 WEEKS AGO", 
    "auther": "天朝特使", 
    "floor": "22225", 
    "url": "http://jandan.net/duan/page-890#comment-3052171", 
    "against": "36", 
    "content": "晚饭后，我舒舒服服的坐在沙 发上看着新闻，我一哥们不停的在我旁边瞎吹牛。“我昨天赚了几百万”、“我和好多明星睡过”…几分钟后，我实在是听不下去这些让人恼火的胡编乱造的谎言，于是我愤怒的走上前去，关掉了《新闻联播》，专心听哥们吹牛。"
  }
]