[
  {
    "zan": "37", 
    "publish_time": "@1 YEAR AGO", 
    "auther": "光消失的地方", 
    "floor": "4024", 
    "url": "http://jandan.net/duan/page-161#comment-2658210", 
    "against": "87", 
    "content": "前方高能：同好们，伪街的时候有试过这样么，昂首挺胸走在灯火阑珊的街上，享受着路人的目光，每个和我擦肩而过的人都能闻到我身上香水的味道，感觉好好。每次出差到陌生的城市必须伪街，反正没人认识我。我这次穿着一双亮色的连裤袜，弹性超好，包裹腿的压力很有快感。看到自己的超短裙和雪白长腿高跟鞋假胸，下面就不自觉石更了起来"
  }, 
  {
    "zan": "70", 
    "publish_time": "@1 YEAR AGO", 
    "auther": "光消失的地方", 
    "floor": "4023", 
    "url": "http://jandan.net/duan/page-161#comment-2658209", 
    "against": "12", 
    "content": "心情不好看看这几句话是不是很舒畅？1）没人看不起你，因为大家根本没看你。2）不用觉得丢人，大家心中的你本来就这样。3）别抱怨上天对你不公，照你的条件，这已经是老天对你最好的安排了。4）谁年轻的时候没傻逼过啊，不过你这么大岁数了还这么傻逼，你能说自己没有创造力吗？"
  }, 
  {
    "zan": "33", 
    "publish_time": "@1 YEAR AGO", 
    "auther": "印度洋", 
    "floor": "4022", 
    "url": "http://jandan.net/duan/page-161#comment-2658107", 
    "against": "37", 
    "content": "失恋和离婚哪个更毁人一点？答案是失恋。因为离婚是想好试好之后的决定，而失恋呢，往往因为一点小错就分手，淘汰率高，其实事情并不是那样的。"
  }, 
  {
    "zan": "204", 
    "publish_time": "@1 YEAR AGO", 
    "auther": "Xavier", 
    "floor": "4021", 
    "url": "http://jandan.net/duan/page-161#comment-2658072", 
    "against": "9", 
    "content": "老板刚才进来，把文件摔到我桌子上：“你做的那个文件，里面能动的图，打印出来怎么就不动了！怎么搞的？重来！”怎么办，想安安心心的上个班真的好难。"
  }, 
  {
    "zan": "311", 
    "publish_time": "@1 YEAR AGO", 
    "auther": "Xavier", 
    "floor": "4020", 
    "url": "http://jandan.net/duan/page-161#comment-2658070", 
    "against": "17", 
    "content": "为什么老美一直不敢惹中国？因为中美之间隔着国际日期变更线，中国今天发射一枚导弹，昨天就打到美国去了，根本来不及拦截。"
  }, 
  {
    "zan": "352", 
    "publish_time": "@1 YEAR AGO", 
    "auther": "Xavier", 
    "floor": "4019", 
    "url": "http://jandan.net/duan/page-161#comment-2658069", 
    "against": "8", 
    "content": "“我只抱着你，什么都不做。”\n“我就摸两下！”\n “让我蹭蹭，绝不进去。”\n“我进去绝对不动，在里面待着就好”\n“我就动两下”\n“…………”\n“你他妈说的两下呢，还差一下啊！！”"
  }, 
  {
    "zan": "93", 
    "publish_time": "@1 YEAR AGO", 
    "auther": "Xavier", 
    "floor": "4018", 
    "url": "http://jandan.net/duan/page-161#comment-2658067", 
    "against": "8", 
    "content": "最讨厌两件事，一是我不接电话对方还打个不停；二是我不停的打电话对方却不接。"
  }, 
  {
    "zan": "194", 
    "publish_time": "@1 YEAR AGO", 
    "auther": "Xavier", 
    "floor": "4017", 
    "url": "http://jandan.net/duan/page-161#comment-2658065", 
    "against": "7", 
    "content": "中通快递的快递员大清早打我电话，一接通后他说：“你好，我是……”， 此时定了几秒，然后来了句“等一下哈，我看一下我是什么通”。"
  }, 
  {
    "zan": "418", 
    "publish_time": "@1 YEAR AGO", 
    "auther": "maylog", 
    "floor": "4016", 
    "url": "http://jandan.net/duan/page-161#comment-2658044", 
    "against": "21", 
    "content": "一个地方有两成的穆斯林，就会开始要求别人尊重他们的习俗，一个地方有四成的穆斯林，就会开始劝别人信教，一个地方有六成的穆斯林，就会开始拿刀逼着其他人信教，一个地方有八成的穆斯林，他们就会分成两派，然后打起来。。。"
  }, 
  {
    "zan": "259", 
    "publish_time": "@1 YEAR AGO", 
    "auther": "光消失的地方", 
    "floor": "4015", 
    "url": "http://jandan.net/duan/page-161#comment-2658033", 
    "against": "22", 
    "content": "记者：有公知说，解放后人的素质不如解放前。您怎么看？王大爷：这完全是胡扯！我举个例子就可以驳倒他。比如解放前闹革命，你要跟群众谈共产主义理想，没人搭理你。你得说抢地、分钱、睡女学生，大伙儿就跟你走了；解放后这么粗俗就不行了，你要想抢地、分钱、睡女学生，得先玩儿命宣传共产主义理想。"
  }, 
  {
    "zan": "56", 
    "publish_time": "@1 YEAR AGO", 
    "auther": "光消失的地方", 
    "floor": "4014", 
    "url": "http://jandan.net/duan/page-161#comment-2658032", 
    "against": "69", 
    "content": "其实美国还有绿卡抽奖。但是不给大陆人（台湾、香港可以）、印度人、墨西哥人抽。大部分欧洲国家都可以抽绿卡，抽中了，直接就给绿卡。我们以前碰到一个波兰人，英文很烂，人家命好，抽奖得了绿卡，全家移民美国。美国每年绿卡抽奖名额很多。"
  }, 
  {
    "zan": "262", 
    "publish_time": "@1 YEAR AGO", 
    "auther": "光消失的地方", 
    "floor": "4013", 
    "url": "http://jandan.net/duan/page-161#comment-2658027", 
    "against": "15", 
    "content": "1月9日，西安市交通局举行出租车调价方案听证会。29名代表，只有一人反对涨价——蓝田县前卫中学政治老师白兵洋。他说，出租车司机收入低，应该降低份子钱，不应该一味提高打车价格，对于消费者不公平。他还说，另外28人全部赞成涨价，不可思议。会后，有人批评他“太冒失”。"
  }, 
  {
    "zan": "169", 
    "publish_time": "@1 YEAR AGO", 
    "auther": "maylog", 
    "floor": "4012", 
    "url": "http://jandan.net/duan/page-161#comment-2658021", 
    "against": "6", 
    "content": "下面给大家朗诵一首现代诗歌，名为《我妈元旦来看我》：我胖了五斤/四天之内/我养的狗也被我妈喂胖了。"
  }, 
  {
    "zan": "60", 
    "publish_time": "@1 YEAR AGO", 
    "auther": "光消失的地方", 
    "floor": "4011", 
    "url": "http://jandan.net/duan/page-161#comment-2658014", 
    "against": "22", 
    "content": "阿拉伯世界，艾哈迈德 . 代伊达特语录：伊思兰最可怕的敌人就是无知的穆思林，因为他的无知和他的行为而变得刻薄，并丑化和破坏了伊斯兰真实的形象，并让世界认为这就是伊思兰。"
  }, 
  {
    "zan": "31", 
    "publish_time": "@1 YEAR AGO", 
    "auther": "Octopus", 
    "floor": "4010", 
    "url": "http://jandan.net/duan/page-161#comment-2657964", 
    "against": "96", 
    "content": "我梦见我一个梦见我室友拿着刀追着我砍，后来被保安制服后吊打。\n想想我都激动的手舞足蹈，活蹦乱跳，暴跳如雷，一蹦3仗高\n但是万万没想到\n我还说梦话被室友听到了\n他把我一下从床上托下来，吊到了电风扇上，拿马桶刷K我。\n（他很丑而且2米1，他叫张自豪）"
  }, 
  {
    "zan": "12", 
    "publish_time": "@1 YEAR AGO", 
    "auther": "周薰", 
    "floor": "4009", 
    "url": "http://jandan.net/duan/page-161#comment-2657906", 
    "against": "63", 
    "content": "我拉个去！看了下露水红颜。我拉个去！漂亮女人就是花钱多！！！！！！！！！！"
  }, 
  {
    "zan": "92", 
    "publish_time": "@1 YEAR AGO", 
    "auther": "光消失的地方", 
    "floor": "4008", 
    "url": "http://jandan.net/duan/page-161#comment-2657880", 
    "against": "93", 
    "content": "重温《盗梦空间》，看到一半睡着了，梦见自己在看《盗梦空间》，正好接着睡前的进度继续看，看到结尾字幕时就醒了，醒来发现电脑也正好播放到了结尾字幕。"
  }, 
  {
    "zan": "90", 
    "publish_time": "@1 YEAR AGO", 
    "auther": "光消失的地方", 
    "floor": "4007", 
    "url": "http://jandan.net/duan/page-161#comment-2657878", 
    "against": "28", 
    "content": "期末考试考场上。老师说，最近作弊现象越来越严重，为了整治不良风气，这次监考他要亲自挂帅。我顿时不知所措：完了，这不就是要挂我吗。"
  }, 
  {
    "zan": "240", 
    "publish_time": "@1 YEAR AGO", 
    "auther": "光消失的地方", 
    "floor": "4006", 
    "url": "http://jandan.net/duan/page-161#comment-2657874", 
    "against": "67", 
    "content": "喜欢就强奸啊，表白有什么用。"
  }, 
  {
    "zan": "135", 
    "publish_time": "@1 YEAR AGO", 
    "auther": "光消失的地方", 
    "floor": "4005", 
    "url": "http://jandan.net/duan/page-161#comment-2657868", 
    "against": "11", 
    "content": "身材苗条跟你抱怨又胖了，成绩优秀跟你抱怨考砸了，收入高跟你抱怨日子没法过了，生活无忧跟你抱怨无聊了，友谊就这样一点一点瓦解了"
  }, 
  {
    "zan": "174", 
    "publish_time": "@1 YEAR AGO", 
    "auther": "光消失的地方", 
    "floor": "4004", 
    "url": "http://jandan.net/duan/page-161#comment-2657859", 
    "against": "26", 
    "content": "刚去散步时，看到一男孩站路边，一女孩抱着个大布偶蹑手蹑脚靠近他，”嗨“地朝他后脑勺一砸，哈哈大笑，男孩转身怒目：“你是不是有病？！”女孩吓到了，然后男孩握住她的手深情地说：“如果不是身体不舒服，怎么打这么轻？”……"
  }, 
  {
    "zan": "193", 
    "publish_time": "@1 YEAR AGO", 
    "auther": "光消失的地方", 
    "floor": "4003", 
    "url": "http://jandan.net/duan/page-161#comment-2657857", 
    "against": "16", 
    "content": "他和他在一起后，承受了太多的不解嘲讽谩骂和诋毁。两人的日子惨淡凄苦，实在是没了活下去的勇气与希望。于是买好了安眠药相约自杀。背着身吃了药后牵手躺在一起，望来世被温柔相待。三个小时后，其中一人起身吻了吻安详沉睡的对方，头也不回的走了。另一人听到关门声后，缓缓睁开了眼。"
  }, 
  {
    "zan": "98", 
    "publish_time": "@1 YEAR AGO", 
    "auther": "光消失的地方", 
    "floor": "4002", 
    "url": "http://jandan.net/duan/page-161#comment-2657854", 
    "against": "5", 
    "content": "女友负气出走，张贴了寻人启事：爱妻昨晚离家，至今未归。人偏胖，五短身材 ，相貌平平，着装邋遢，沟通能力差脾气暴躁。请好心人留意，有重谢100人民币，末尾附了一 张她的身份证照。刚贴完不到10分钟女友就回来了。"
  }, 
  {
    "zan": "200", 
    "publish_time": "@1 YEAR AGO", 
    "auther": "光消失的地方", 
    "floor": "4001", 
    "url": "http://jandan.net/duan/page-161#comment-2657853", 
    "against": "6", 
    "content": "不要说“你太黑不适合这款粉底”，要说“你用这款粉底显得皮肤黑”；不要说“你腿型不好穿不了这条裤子”，要说“你穿上这裤子显得腿型不好”；不要说“你有肚子穿不住这件衣服”，要说“你穿这件衣服显得肚子有点鼓”；记住，一定要把责任推卸给衣服裤子和化妆品，而她本身，一定是完美无缺的。"
  }, 
  {
    "zan": "61", 
    "publish_time": "@1 YEAR AGO", 
    "auther": "光消失的地方", 
    "floor": "4000", 
    "url": "http://jandan.net/duan/page-161#comment-2657838", 
    "against": "3", 
    "content": "朋友家养了只鹦鹉特别聪明。我说：“你好！” 它说：“你好！” 我说：“见到你很高兴。” 它说：“见到你很高兴。” 我说：“我长得很丑。” 它说：“嗯嗯嗯。”"
  }
]