[
  {
    "zan": "144", 
    "publish_time": "@3 WEEKS AGO", 
    "auther": "天朝特使", 
    "floor": "22224", 
    "url": "http://jandan.net/duan/page-889#comment-3052165", 
    "against": "24", 
    "content": "老公在英国公干一年半，昨天终于回家，半夜睡觉说了句梦话“亲爱的我想要了”，这本来没什么的，可偏偏他说这句话的时候屁股撅的老高……"
  }, 
  {
    "zan": "136", 
    "publish_time": "@3 WEEKS AGO", 
    "auther": "天朝特使", 
    "floor": "22223", 
    "url": "http://jandan.net/duan/page-889#comment-3052159", 
    "against": "12", 
    "content": "老家在湖边，小时候在湖里野，难免会被蚂蟥吸附，土办法就是用鞋底子抽，还记得那年夏天，我和几个小伙伴去湖里游泳。我蛋蛋上沾了一个蚂蟥，当时真吓坏了。我到现在都没忘记几个小伙伴用拖鞋猛抽的画面。"
  }, 
  {
    "zan": "89", 
    "publish_time": "@3 WEEKS AGO", 
    "auther": "天朝特使", 
    "floor": "22222", 
    "url": "http://jandan.net/duan/page-889#comment-3052148", 
    "against": "11", 
    "content": "异地恋，上个礼拜和她微 信聊天，突然问我：“粮食存了多少？”我一听来劲了，回她说：“存得满满的，时刻准备着！”于是我憋了一个礼拜，今天陪她逛了一天的街，花光了口袋里的钱。"
  }, 
  {
    "zan": "134", 
    "publish_time": "@3 WEEKS AGO", 
    "auther": "快乐精品秀", 
    "floor": "22221", 
    "url": "http://jandan.net/duan/page-889#comment-3052103", 
    "against": "29", 
    "content": "儿孑看报纸，随口问我，爸，党委、政府、人大、政协都是干啥的呀?想了半天告诉儿子：党委呢，就像是你妈，说了算，还老是骂人，政府就係是我，整天干话，还要被你妈骂来骂去，人大就像是你爷爷，名义上是一家之主，整天就出去下棋，啥事也不管，政协和你奶奶差不多，整天唠唠叨叼，但是家里人都不听，明自了吧儿子。"
  }, 
  {
    "zan": "78", 
    "publish_time": "@3 WEEKS AGO", 
    "auther": "大大", 
    "floor": "22220", 
    "url": "http://jandan.net/duan/page-889#comment-3052102", 
    "against": "478", 
    "content": "一对情侣在影院。女孩说，“我去尿尿，可以挤过去吗？ ”男孩说：“别了，你这么漂亮，挤过去肯定有人摸你，这里这么黑，就蹲这尿吧。”她脱下裤子开尿。男孩儿不由自主地去摸女孩下面。于是他摸到了又长又硬的东西，说：“ 啊 ！你！你！你是男的？！ ” “不是，我改变了主意，我决定大便"
  }, 
  {
    "zan": "18", 
    "publish_time": "@3 WEEKS AGO", 
    "auther": "大大", 
    "floor": "22219", 
    "url": "http://jandan.net/duan/page-889#comment-3052098", 
    "against": "352", 
    "content": "一对情侣在影院。女孩说，“我去尿尿，可以挤过去吗？ ”男孩说：“别了，你这么漂亮，挤过去肯定有人摸你，这里这么黑，就蹲这尿吧。”她脱下裤子开尿。男孩儿不由自主地去摸女孩下面。于是他摸到了又长又硬的东西，说：“ 啊 ！你！你！你是男的？！ ” “不是，我改变了主意，我决定大便"
  }, 
  {
    "zan": "196", 
    "publish_time": "@3 WEEKS AGO", 
    "auther": "光消失的地方", 
    "floor": "22218", 
    "url": "http://jandan.net/duan/page-889#comment-3052093", 
    "against": "11", 
    "content": "妈妈：过年什么时候放假啊？\n儿子：还不知道呢。我有多长时间没回家了？\n妈妈：昨天杀毒软件提醒“您的电脑已经76天没有体检了”，你应该是有76天没回家了。"
  }, 
  {
    "zan": "307", 
    "publish_time": "@3 WEEKS AGO", 
    "auther": "光消失的地方", 
    "floor": "22217", 
    "url": "http://jandan.net/duan/page-889#comment-3052092", 
    "against": "22", 
    "content": "去女神家里修笔记本，我见没空椅子就坐她床上修，她却质问我：“你裤子那么脏怎么坐我床上？”\n我很尴尬只好把裤子脱了。\n女神见状急了骂道：“我是说你怎么坐我床上了？”\n于是我只好躺下了。"
  }, 
  {
    "zan": "150", 
    "publish_time": "@3 WEEKS AGO", 
    "auther": "快乐精品秀", 
    "floor": "22216", 
    "url": "http://jandan.net/duan/page-889#comment-3052073", 
    "against": "8", 
    "content": "报载：一男单身狗欲以每天2千元的价格租一女友回家过年，在网上发一招骋启示，应征者众。\n其中一美女由男友陪同面试通过，两人卿卿我我，如生死离别\n真是天下之大无奇不有"
  }, 
  {
    "zan": "205", 
    "publish_time": "@3 WEEKS AGO", 
    "auther": "快乐精品秀", 
    "floor": "22215", 
    "url": "http://jandan.net/duan/page-889#comment-3052061", 
    "against": "15", 
    "content": "你们都是骗子！！！！！！！都说过年不看春晚要买一本西游记过年看，我进了一大堆西游记盘，特么一周了，一张都没卖出去，骗子！！！！！！！！！！！！！！！"
  }, 
  {
    "zan": "28", 
    "publish_time": "@3 WEEKS AGO", 
    "auther": "光消失的地方", 
    "floor": "22214", 
    "url": "http://jandan.net/duan/page-889#comment-3052060", 
    "against": "109", 
    "content": "Fenng： 计算机领域，几乎是信息最对称的一个行业了，别死守着学校混文凭了，你要学的，到处都能学到，少数高精尖的东西例外，但你也不是那块料。我还是那句话，绝大多数读研究生的都是在补贴社会，这里面还有一部分在补贴导师。读研究生，把路混窄了。换一条路，不差"
  }, 
  {
    "zan": "34", 
    "publish_time": "@3 WEEKS AGO", 
    "auther": "光消失的地方", 
    "floor": "22213", 
    "url": "http://jandan.net/duan/page-889#comment-3052058", 
    "against": "102", 
    "content": "老子撸了10000多把联盟,坑了9000多局,精通各种辱骂队友方式,卖队友达三万个,熟练掌握抢人头时机。老子尸体躺过召唤师峡谷每一个角落,练成极限送人头方法一千余种,拥有各种挂机理由800多个。你们在萌萌,老子把你们区的最强王者全坑成青铜五,老子文能挂机喷队友,武能越塔送人头,进可孤身一挑五,退可坐等二十投,前能飞脚救残敌"
  }, 
  {
    "zan": "227", 
    "publish_time": "@3 WEEKS AGO", 
    "auther": "光消失的地方", 
    "floor": "22212", 
    "url": "http://jandan.net/duan/page-889#comment-3051999", 
    "against": "14", 
    "content": "很多时候亲戚问长问短并不是真的关心你，他们只是想确保自家小孩过得比你好；而那些真正关心你的亲戚，感情都在压岁钱里。"
  }, 
  {
    "zan": "181", 
    "publish_time": "@3 WEEKS AGO", 
    "auther": "双人花样撸", 
    "floor": "22211", 
    "url": "http://jandan.net/duan/page-889#comment-3051992", 
    "against": "20", 
    "content": "刚在电视上看到一个真事，堪称段子好题材。\n一个22岁姓史的农村穷吊丝特爱“炫富”，在外逢人就吹自己家庭多富有，父亲、叔叔年收入几百万，嘴瘾甚欢、乐此不疲。于是就有同为吊丝的张某信以为真并处心积虑三个月取得信任终将其绑架。而当张某打电话给史吊的叔叔勒索“巨款”15万时傻眼了，史叔叔竟然嘲笑他“香港电影看多了吧？还撕票？随便吧！”然后就挂断了。\n话说这史吊的真实家境别说15万，就连15元也要翻箱倒柜，是个地地道道的穷苦农民家庭。所以史叔叔一听勒索电话就笑了：嘿，这世道，还有人拿我这样的开玩笑呢，呵呵。\n这还得了，张某气愤坏了，一冲动就真把史吊杀了，还分尸焚烧，然后埋在屎坑里，也算史得其所，对得起他了。"
  }, 
  {
    "zan": "206", 
    "publish_time": "@3 WEEKS AGO", 
    "auther": "soxsox", 
    "floor": "22210", 
    "url": "http://jandan.net/duan/page-889#comment-3051991", 
    "against": "25", 
    "content": "女儿睡醒哭了，我怎么哄都不行，肯定是饿了，可是媳妇还坐在床上，跟没事人似的。我抱着孩子过去刚要开骂，只见老婆从胸前掏出个热水袋说“递过来吧”。\n原来是在“热奶”，这么冷的天。。这么是难为她了。"
  }, 
  {
    "zan": "257", 
    "publish_time": "@3 WEEKS AGO", 
    "auther": "soxsox", 
    "floor": "22209", 
    "url": "http://jandan.net/duan/page-889#comment-3051979", 
    "against": "17", 
    "content": "一对夫妻连续生了三个孩子都是女儿，为了体恤妻子，丈夫便说：老婆咱别生了吧，男孩女孩都一样。老婆说：不！我要生！老娘非得看看你上辈子究竟有几个情人。"
  }, 
  {
    "zan": "99", 
    "publish_time": "@3 WEEKS AGO", 
    "auther": "soxsox", 
    "floor": "22208", 
    "url": "http://jandan.net/duan/page-889#comment-3051978", 
    "against": "24", 
    "content": "老王病危，临终之前把小王叫到跟前说：孩子啊，我死后对外说是得艾滋病死的，不要说是癌症死的，记住了不？小王：为什么啊？老王：这样就没人敢动你妈了！"
  }, 
  {
    "zan": "94", 
    "publish_time": "@3 WEEKS AGO", 
    "auther": "standthere", 
    "floor": "22207", 
    "url": "http://jandan.net/duan/page-889#comment-3051940", 
    "against": "24", 
    "content": "鲁肃追问孔明：“先生真神人也！何以知今日如此大雾？”孔明曰：为将而不通天文，不识地利，不知奇门，不晓阴阳，不看阵图，不明兵势，请问你的青春被狗吃了吗？”"
  }, 
  {
    "zan": "60", 
    "publish_time": "@3 WEEKS AGO", 
    "auther": "光消失的地方", 
    "floor": "22206", 
    "url": "http://jandan.net/duan/page-889#comment-3051920", 
    "against": "21", 
    "content": "唐僧第一次见悟空的时候问他是不是从一个叫做美国的地方来，悟空摇摇头。唐僧又问悟空觉得自己长得好看吗，悟空摇摇头。唐僧：那你为什么叫美猴王？"
  }, 
  {
    "zan": "108", 
    "publish_time": "@3 WEEKS AGO", 
    "auther": "光消失的地方", 
    "floor": "22205", 
    "url": "http://jandan.net/duan/page-889#comment-3051873", 
    "against": "36", 
    "content": "【心塞！#银行接线猿吐槽#：上海人最难伺候[笑cry]】小张在某银行当客服，他从接过的电话中，发现了不少规律：上海用户最难伺候，不爱说普通话；重庆用户好说话；广东用户睡得晚；山东用户起得早。存款几十万的客户，会理性沟通；爱投诉的客户，多半卡里不超1万元。（华龙网）"
  }, 
  {
    "zan": "130", 
    "publish_time": "@3 WEEKS AGO", 
    "auther": "猴赛雷", 
    "floor": "22204", 
    "url": "http://jandan.net/duan/page-889#comment-3051842", 
    "against": "20", 
    "content": "“XX的XX得了XX病需要巨款治疗，请大家献爱心捐款”。\n说实话不是我冷漠对于一个八竿子打不着的人在朋友圈这种信息我是连看都懒得看，更别说给钱了，而且这种风气任由蔓延迟早会沦为不法分子骗钱的途径，越来越觉得这种东西的讨厌程度快要赶上卖面膜的微商了，希望这种朋友圈乞丐快点消失。"
  }, 
  {
    "zan": "38", 
    "publish_time": "@3 WEEKS AGO", 
    "auther": "光消失的地方", 
    "floor": "22203", 
    "url": "http://jandan.net/duan/page-889#comment-3051831", 
    "against": "54", 
    "content": "把过年的时间改到夏天，不就无需春运了吗？"
  }, 
  {
    "zan": "37", 
    "publish_time": "@3 WEEKS AGO", 
    "auther": "光消失的地方", 
    "floor": "22202", 
    "url": "http://jandan.net/duan/page-889#comment-3051829", 
    "against": "17", 
    "content": "我对人从来都是你进一步我进两步，你退一步我退一万步，朋友也是，超级怕尴尬，一旦觉得自己在别人心目中没有自己想象的地位，就想立刻远离，什么毛病啊这是。。。"
  }, 
  {
    "zan": "54", 
    "publish_time": "@3 WEEKS AGO", 
    "auther": "光消失的地方", 
    "floor": "22201", 
    "url": "http://jandan.net/duan/page-889#comment-3051823", 
    "against": "4", 
    "content": "想吃点啥就吃点啥吧，因为下周外卖就逐渐放假了啊！"
  }, 
  {
    "zan": "41", 
    "publish_time": "@3 WEEKS AGO", 
    "auther": "南京大萝卜", 
    "floor": "22200", 
    "url": "http://jandan.net/duan/page-889#comment-3051820", 
    "against": "106", 
    "content": "扫黄就是鼓励强奸，肃贪就是消灭异己。"
  }
]