[
  {
    "zan": "31", 
    "publish_time": "@1 MONTH AGO", 
    "auther": "快乐精品秀", 
    "floor": "21299", 
    "url": "http://jandan.net/duan/page-852#comment-3035686", 
    "against": "46", 
    "content": "上帝问肖邦：\n你能弹出一首\n中国股民对A股那般忧伤的曲子么？\n肖邦摇摇头。\n上帝对肖邦说：\n有一个人可以弹奏出来\n就是你兄弟肖钢！\n肖邦摇摇头说：\n我俩不一样，\n我有谱、他没谱！"
  }, 
  {
    "zan": "267", 
    "publish_time": "@1 MONTH AGO", 
    "auther": "光消失的地方", 
    "floor": "21298", 
    "url": "http://jandan.net/duan/page-852#comment-3035654", 
    "against": "5", 
    "content": "一男子走进一家小店，他问老板：“你还记得我吗？”老板摇了摇头。男人说：“我早就知道，你早把我忘了，但是我不会忘记！十年前，我曾经身无分文，走进你的店，向你讨了二十块钱，买了车票，去城市打拼！”老板笑笑：“没想到你一直记的啊，竟然记了十年，其实帮助人是应该的，而且也没多少钱………”男人又说：“那好，你能再借我二十块钱吗？…………”"
  }, 
  {
    "zan": "10", 
    "publish_time": "@1 MONTH AGO", 
    "auther": "winkcat", 
    "floor": "21297", 
    "url": "http://jandan.net/duan/page-852#comment-3035631", 
    "against": "167", 
    "content": "猹闻闰土父子已被擒获，大喜，聚众将于帐中。\n少时，角鸡簇拥闰土至前。猹曰：“孤久慕将军盛德，欲结秦、晋之好，何相弃耶？公平昔自以为天下无敌，今日何由被吾所擒？将军今日还服猹否？”\n闰土厉声骂曰：“碧眼小儿，紫髯鼠辈！吾与鲁迅瓜园结义，誓扶周家，岂与汝叛汉之贼为伍耶！我今误中奸计，有死而已，何必多言！”\n猹回顾众官曰：“闰土世之豪杰，孤深爱之。今欲以礼相待，劝使归降，何如？”\n主簿稻鸡曰：“不可。昔杨二嫂得此人时，封侯赐爵，三日一小宴，五日一大宴，上马一提金，下马一提银：如此恩礼，毕竟留之不住，听其斩关杀将而去，致使今日反为所逼，几欲迁都以避其锋。今主公既已擒之，若不即除，恐贻后患。”\n猹沉吟半晌，曰：“斯言是也。”遂命推出。于是闰土父子皆遇害。"
  }, 
  {
    "zan": "69", 
    "publish_time": "@1 MONTH AGO", 
    "auther": "喝醉的小熊", 
    "floor": "21296", 
    "url": "http://jandan.net/duan/page-852#comment-3035626", 
    "against": "5", 
    "content": "看着众多领导纷纷表示听不懂我的展示，我笑了。\nMD老子都不知道自己在讲什么，你们怎么可能听懂？"
  }, 
  {
    "zan": "96", 
    "publish_time": "@1 MONTH AGO", 
    "auther": "远方的云雨", 
    "floor": "21295", 
    "url": "http://jandan.net/duan/page-852#comment-3035623", 
    "against": "15", 
    "content": "包拯要给女儿起名字，于是求助于公孙策。包拯说：当初我母亲给我起名叫包拯，是为了让我拯救苍生，我也想在我女儿的名字中体现出造福天下。你说叫什么好呢？公孙策想想后说：就叫包邮吧！这个名字好！"
  }, 
  {
    "zan": "155", 
    "publish_time": "@1 MONTH AGO", 
    "auther": "远方的云雨", 
    "floor": "21294", 
    "url": "http://jandan.net/duan/page-852#comment-3035621", 
    "against": "14", 
    "content": "今天躺倒床上对老公说：我这几天才发现我是个同性恋！老公惊恐的看着我说：为什么？我：每天看到我们领导，我都想艹他妈！"
  }, 
  {
    "zan": "301", 
    "publish_time": "@1 MONTH AGO", 
    "auther": "远方的云雨", 
    "floor": "21293", 
    "url": "http://jandan.net/duan/page-852#comment-3035619", 
    "against": "11", 
    "content": "观音对唐僧道：“你这一去，要走上十万八千里，途经九九八十一难方能抵达西天、取得真经。”\n唐僧双手合十道：“阿弥陀佛，剧透死全家。"
  }, 
  {
    "zan": "16", 
    "publish_time": "@1 MONTH AGO", 
    "auther": "winkcat", 
    "floor": "21292", 
    "url": "http://jandan.net/duan/page-852#comment-3035611", 
    "against": "130", 
    "content": "从前有一只蛤蟆，爬到山坡上看日出，遇到了从对面上来同样打算看日出的大狗，因为山坡只有一条路可以看日出，于是蛤蟆让给大狗一些位置，大狗趁机将蛤蟆了下去，受了伤的蛤蟆无奈只有骑两匹马走回去。太阳落山了，大狗第二次再来时，已经不见了蛤蟆，它不止看了个够，还让亲朋好友都来看，霸占位置不愿意让两侧的小动物们通行，最终引起了猎人的注意，把它一家都抓住剥了皮。"
  }, 
  {
    "zan": "49", 
    "publish_time": "@1 MONTH AGO", 
    "auther": "光消失的地方", 
    "floor": "21291", 
    "url": "http://jandan.net/duan/page-852#comment-3035568", 
    "against": "46", 
    "content": "男孩羞羞地问女孩：“你是我的小公举，那我是你的小王几？”女孩淡淡地回答：“八，你是我的小王八。”"
  }, 
  {
    "zan": "38", 
    "publish_time": "@1 MONTH AGO", 
    "auther": "光消失的地方", 
    "floor": "21290", 
    "url": "http://jandan.net/duan/page-852#comment-3035567", 
    "against": "43", 
    "content": "这世界上最赞的10件事：1. 天气冷洗热水澡；2. 肚子饿时狼吞虎咽；3. 温暖的拥抱；4. 累了一天后倒在床上；5. 额头的一吻；6. 睡到自然醒；7. 不用考试；8. 暗恋的人也喜欢你；9. 偶像跟你说话；10. 撕开全新商品保护膜。"
  }, 
  {
    "zan": "94", 
    "publish_time": "@1 MONTH AGO", 
    "auther": "光消失的地方", 
    "floor": "21289", 
    "url": "http://jandan.net/duan/page-852#comment-3035564", 
    "against": "8", 
    "content": "如果你躺在床上翻来覆去的睡不着，不妨试试去躺在地上一会儿再回到床上，然后你就会发现还是躲在被窝里舒服，然后你就可以很快睡着了。"
  }, 
  {
    "zan": "168", 
    "publish_time": "@1 MONTH AGO", 
    "auther": "光消失的地方", 
    "floor": "21288", 
    "url": "http://jandan.net/duan/page-852#comment-3035563", 
    "against": "8", 
    "content": "朋友被逼相亲，加了男方秋秋之后对方给她发了个长达86页的自我介绍屁屁踢。姑娘说自己当了四年乙方，现在终于体会到了当甲方的滋味。"
  }, 
  {
    "zan": "126", 
    "publish_time": "@1 MONTH AGO", 
    "auther": "光消失的地方", 
    "floor": "21287", 
    "url": "http://jandan.net/duan/page-852#comment-3035562", 
    "against": "12", 
    "content": "发现一个问题，在冬天的东北户外，呼出的哈气总会干扰你的视线，如果你想看清一个人，必须要屏住呼吸，暂停哈气，所以你冒着窒息危险想看清的人，一定是非常吸引你的人，这可能就是“美的令人窒息”一词儿的由来。"
  }, 
  {
    "zan": "26", 
    "publish_time": "@1 MONTH AGO", 
    "auther": "光消失的地方", 
    "floor": "21286", 
    "url": "http://jandan.net/duan/page-852#comment-3035559", 
    "against": "35", 
    "content": "近日，成都龙江路小学的詹夏瑞同学，写了篇爆笑作文：一家人旅游时停车吃烤串，爸妈吃完就走完全忘了他！他当即吓哭，烤串老板帮忙联系爸妈后，“我愤愤地质问，我还是不是亲生儿子！”"
  }, 
  {
    "zan": "64", 
    "publish_time": "@1 MONTH AGO", 
    "auther": "光消失的地方", 
    "floor": "21285", 
    "url": "http://jandan.net/duan/page-852#comment-3035555", 
    "against": "11", 
    "content": "【当街吵架后女友躺地不动 被过路车碾压】去年11月底，重庆梁平县一女孩，在街上与男友吵架，见男友扭头要走，她干脆躺地不动，不料正好被一过路黑色轿车碾压，其肋骨、盆骨骨折、头部受伤。目前，女孩正住院治疗，懊悔道：“再选一次，我们绝不会在大街上吵架！"
  }, 
  {
    "zan": "20", 
    "publish_time": "@1 MONTH AGO", 
    "auther": "快乐精品秀", 
    "floor": "21284", 
    "url": "http://jandan.net/duan/page-852#comment-3035529", 
    "against": "113", 
    "content": "看到很多喷乐视的帖子，我就忍不住了。要不是乐视，不知道有多少青少年要精尽人亡了，乐视拯救了多少青少年知道吗？年轻人就知道撸，等你到了30岁，就能明白我为什么要顶乐视了。不说了，男子医院到了。"
  }, 
  {
    "zan": "61", 
    "publish_time": "@1 MONTH AGO", 
    "auther": "快乐精品秀", 
    "floor": "21283", 
    "url": "http://jandan.net/duan/page-852#comment-3035525", 
    "against": "9", 
    "content": "张无忌跌下悬崖，练就了九阳神功。杨过跌下悬崖，练就了一身好内力。段誉跌下悬崖，练就了凌波微步。\n现在我正在悬崖边上，不知道跳下去会练就什么神功……"
  }, 
  {
    "zan": "57", 
    "publish_time": "@1 MONTH AGO", 
    "auther": "远方的云雨", 
    "floor": "21282", 
    "url": "http://jandan.net/duan/page-852#comment-3035521", 
    "against": "32", 
    "content": "我越来越觉得缴纳社保跟买彩票差不多了。\n社保是不是现支现付？是不是庞氏骗局？\n社会是不是越来越老龄化？\n为什么不废止计划生育？（剥夺人基本的生育权）\n我只是不想让国家来帮我养老了，我自己养自己行不行？"
  }, 
  {
    "zan": "74", 
    "publish_time": "@1 MONTH AGO", 
    "auther": "", 
    "floor": "21281", 
    "url": "http://jandan.net/duan/page-852#comment-3035512", 
    "against": "18", 
    "content": "国内这些软件……不知道为什么越到后面越是要往综合向发展。你们就不能像最开始那样各司其职吗？杀毒的就杀毒，聊天的就聊天，当钱包的就当钱包，不要总想十八般武艺样样通，还互相打架互相撕扯，烦死了好吗。我请个保姆只是想劳烦她打扫卫生做做家务，并不想看她表演劈叉碎石跳火圈或者托马斯回旋。（@风息神泪）"
  }, 
  {
    "zan": "48", 
    "publish_time": "@1 MONTH AGO", 
    "auther": "", 
    "floor": "21280", 
    "url": "http://jandan.net/duan/page-852#comment-3035510", 
    "against": "24", 
    "content": "不要小瞧吃软饭的男人，他们靠的都是很硬的本事。"
  }, 
  {
    "zan": "61", 
    "publish_time": "@1 MONTH AGO", 
    "auther": "", 
    "floor": "21279", 
    "url": "http://jandan.net/duan/page-852#comment-3035509", 
    "against": "11", 
    "content": "@fannyandfly_523：这个时候，马化腾出现了，当金角大王举起宝葫芦对着马化腾时，马化腾也拿出了一个一模一样的宝葫芦，对金角大王说，你的那个是假的！我的才是真正的宝葫芦，然后把金角大王和银角大王都吸了进去。"
  }, 
  {
    "zan": "200", 
    "publish_time": "@1 MONTH AGO", 
    "auther": "", 
    "floor": "21278", 
    "url": "http://jandan.net/duan/page-852#comment-3035507", 
    "against": "6", 
    "content": "@Scswga：和老公一起看电影《超完美谋杀案》，看到一半时他对我说：“我有点害怕。”我问：“我都不怕，你个大男人还怕？”他犹豫地说：“那倒不是，你别记笔记了，好吗？”"
  }, 
  {
    "zan": "100", 
    "publish_time": "@1 MONTH AGO", 
    "auther": "快乐精品秀", 
    "floor": "21277", 
    "url": "http://jandan.net/duan/page-852#comment-3035505", 
    "against": "3", 
    "content": "某人给室友说，别整天宅着啊！都快废了，得出去走走。那人觉得有道理，然后就出去了，结果第二天就被抓回来了，还多判了5年！！"
  }, 
  {
    "zan": "63", 
    "publish_time": "@1 MONTH AGO", 
    "auther": "光消失的地方", 
    "floor": "21276", 
    "url": "http://jandan.net/duan/page-852#comment-3035503", 
    "against": "5", 
    "content": "近来看到的最心疼的新闻：芬兰的森林公园护林员一年中75%的工作，是在茫茫林海中搜救因拍专辑封面而迷路的重金属乐队成员……就不能老老实实在家练琴吗"
  }, 
  {
    "zan": "75", 
    "publish_time": "@1 MONTH AGO", 
    "auther": "光消失的地方", 
    "floor": "21275", 
    "url": "http://jandan.net/duan/page-852#comment-3035502", 
    "against": "14", 
    "content": "校园乐队专场上刚唱两首歌，主持人热场介绍乐队成员。介绍主唱，主唱飙了段高音，介绍吉他手，吉他手飙了段solo，介绍鼓手，鼓手飙了段solo，介绍键盘手，键盘手飙了段solo，介绍贝斯手，贝斯手飙了段街舞"
  }
]